{
  "market_regime": {
    "regime": "BEARISH",
    "details": {
      "spy_price": 631.97,
      "spy_vs_50ma": -6.61,
      "spy_vs_200ma": -3.98,
      "qqq_price": 558.28,
      "qqq_vs_50ma": -7.75,
      "vix": 30.61
    },
    "modifier": 0.4
  },
  "signals": [
    {
      "ticker": "AMD",
      "sector": "NASDAQ_Tech",
      "signal": "HOLD",
      "confidence": 21,
      "composite_score": 0.014,
      "current_price": 196.04,
      "daily_change": -2.95,
      "buy_range": "$182.14 - $191.41",
      "sell_range": "$200.67 - $214.57",
      "support": 188.22,
      "resistance": 221.33,
      "indicators": {
        "rsi": 45.0,
        "macd_hist": 0.7857,
        "bb_position": 31.2,
        "vs_sma50": -8.09,
        "volume_ratio": 1.18,
        "stoch_k": 13.0
      },
      "individual_scores": {
        "rsi": 0.0,
        "macd": 0.5,
        "bollinger": 0.0,
        "ma": -0.4,
        "volume": 0.1,
        "stochastic": 0.0
      },
      "timestamp": "2026-03-30T20:56:52.291695"
    },
    {
      "ticker": "AMZN",
      "sector": "NASDAQ_Tech",
      "signal": "HOLD",
      "confidence": 34,
      "composite_score": -0.146,
      "current_price": 200.95,
      "daily_change": 0.81,
      "buy_range": "$193.05 - $198.32",
      "sell_range": "$203.58 - $211.48",
      "support": 199.14,
      "resistance": 220.47,
      "indicators": {
        "rsi": 36.7,
        "macd_hist": -0.5798,
        "bb_position": 2.5,
        "vs_sma50": -7.16,
        "volume_ratio": 0.95,
        "stoch_k": 10.1
      },
      "individual_scores": {
        "rsi": 0.0,
        "macd": -1.0,
        "bollinger": 0.8,
        "ma": -1.0,
        "volume": -0.1,
        "stochastic": 0.5
      },
      "timestamp": "2026-03-30T20:56:52.390860"
    },
    {
      "ticker": "ANET",
      "sector": "NASDAQ_Tech",
      "signal": "HOLD",
      "confidence": 33,
      "composite_score": -0.13,
      "current_price": 116.13,
      "daily_change": -3.84,
      "buy_range": "$107.38 - $113.21",
      "sell_range": "$119.05 - $127.8",
      "support": 115.42,
      "resistance": 141.77,
      "indicators": {
        "rsi": 27.0,
        "macd_hist": -1.866,
        "bb_position": -13.1,
        "vs_sma50": -13.96,
        "volume_ratio": 0.95,
        "stoch_k": 2.8
      },
      "individual_scores": {
        "rsi": 0.197,
        "macd": -1.0,
        "bollinger": 0.8,
        "ma": -1.0,
        "volume": -0.1,
        "stochastic": 0.5
      },
      "timestamp": "2026-03-30T20:56:52.572343"
    },
    {
      "ticker": "GOOG",
      "sector": "NASDAQ_Tech",
      "signal": "HOLD",
      "confidence": 21,
      "composite_score": -0.018,
      "current_price": 273.14,
      "daily_change": -0.23,
      "buy_range": "$262.91 - $269.73",
      "sell_range": "$276.55 - $286.78",
      "support": 271.54,
      "resistance": 311.07,
      "indicators": {
        "rsi": 18.7,
        "macd_hist": -2.8265,
        "bb_position": -6.6,
        "vs_sma50": -12.49,
        "volume_ratio": 1.07,
        "stoch_k": 4.1
      },
      "individual_scores": {
        "rsi": 0.756,
        "macd": -1.0,
        "bollinger": 0.8,
        "ma": -0.4,
        "volume": 0.1,
        "stochastic": 0.5
      },
      "timestamp": "2026-03-30T20:56:52.735374"
    },
    {
      "ticker": "GOOGL",
      "sector": "NASDAQ_Tech",
      "signal": "HOLD",
      "confidence": 22,
      "composite_score": -0.028,
      "current_price": 273.5,
      "daily_change": -0.31,
      "buy_range": "$262.91 - $269.97",
      "sell_range": "$277.03 - $287.62",
      "support": 272.11,
      "resistance": 312.47,
      "indicators": {
        "rsi": 20.7,
        "macd_hist": -2.9599,
        "bb_position": -7.1,
        "vs_sma50": -12.41,
        "volume_ratio": 1.14,
        "stoch_k": 3.4
      },
      "individual_scores": {
        "rsi": 0.62,
        "macd": -1.0,
        "bollinger": 0.8,
        "ma": -0.4,
        "volume": 0.1,
        "stochastic": 0.5
      },
      "timestamp": "2026-03-30T20:56:52.915826"
    },
    {
      "ticker": "IONQ",
      "sector": "NASDAQ_Tech",
      "signal": "HOLD",
      "confidence": 27,
      "composite_score": -0.078,
      "current_price": 26.59,
      "daily_change": -3.34,
      "buy_range": "$23.63 - $25.6",
      "sell_range": "$27.58 - $30.54",
      "support": 25.9,
      "resistance": 38.24,
      "indicators": {
        "rsi": 17.2,
        "macd_hist": -0.4622,
        "bb_position": -7.1,
        "vs_sma50": -26.88,
        "volume_ratio": 0.91,
        "stoch_k": 6.9
      },
      "individual_scores": {
        "rsi": 0.852,
        "macd": -1.0,
        "bollinger": 0.8,
        "ma": -1.0,
        "volume": -0.1,
        "stochastic": 0.5
      },
      "timestamp": "2026-03-30T20:56:53.006549"
    },
    {
      "ticker": "META",
      "sector": "NASDAQ_Tech",
      "signal": "HOLD",
      "confidence": 28,
      "composite_score": -0.083,
      "current_price": 536.38,
      "daily_change": 2.03,
      "buy_range": "$507.87 - $526.88",
      "sell_range": "$545.88 - $574.39",
      "support": 520.26,
      "resistance": 672.19,
      "indicators": {
        "rsi": 19.7,
        "macd_hist": -9.5718,
        "bb_position": 2.3,
        "vs_sma50": -16.38,
        "volume_ratio": 1.45,
        "stoch_k": 11.7
      },
      "individual_scores": {
        "rsi": 0.687,
        "macd": -1.0,
        "bollinger": 0.8,
        "ma": -1.0,
        "volume": 0.1,
        "stochastic": 0.5
      },
      "timestamp": "2026-03-30T20:56:53.114812"
    },
    {
      "ticker": "MU",
      "sector": "NASDAQ_Tech",
      "signal": "HOLD",
      "confidence": 27,
      "composite_score": -0.07,
      "current_price": 321.8,
      "daily_change": -9.92,
      "buy_range": "$281.43 - $308.34",
      "sell_range": "$335.26 - $375.63",
      "support": 318.42,
      "resistance": 471.34,
      "indicators": {
        "rsi": 32.2,
        "macd_hist": -12.037,
        "bb_position": -5.8,
        "vs_sma50": -20.43,
        "volume_ratio": 1.58,
        "stoch_k": 2.2
      },
      "individual_scores": {
        "rsi": 0.0,
        "macd": -1.0,
        "bollinger": 0.8,
        "ma": -0.4,
        "volume": 0.3,
        "stochastic": 0.5
      },
      "timestamp": "2026-03-30T20:56:53.306952"
    },
    {
      "ticker": "NET",
      "sector": "NASDAQ_Tech",
      "signal": "HOLD",
      "confidence": 28,
      "composite_score": -0.086,
      "current_price": 194.63,
      "daily_change": -4.13,
      "buy_range": "$178.39 - $189.22",
      "sell_range": "$200.04 - $216.28",
      "support": 171.62,
      "resistance": 229.15,
      "indicators": {
        "rsi": 42.1,
        "macd_hist": -2.2234,
        "bb_position": 24.9,
        "vs_sma50": 2.28,
        "volume_ratio": 0.99,
        "stoch_k": 8.8
      },
      "individual_scores": {
        "rsi": 0.0,
        "macd": -1.0,
        "bollinger": 0.3,
        "ma": 0.0,
        "volume": -0.1,
        "stochastic": 0.0
      },
      "timestamp": "2026-03-30T20:56:53.412067"
    },
    {
      "ticker": "NVDA",
      "sector": "NASDAQ_Tech",
      "signal": "HOLD",
      "confidence": 31,
      "composite_score": -0.117,
      "current_price": 165.17,
      "daily_change": -1.4,
      "buy_range": "$157.53 - $162.62",
      "sell_range": "$167.72 - $175.36",
      "support": 164.27,
      "resistance": 188.88,
      "indicators": {
        "rsi": 26.1,
        "macd_hist": -1.4282,
        "bb_position": -8.4,
        "vs_sma50": -9.77,
        "volume_ratio": 1.02,
        "stoch_k": 3.7
      },
      "individual_scores": {
        "rsi": 0.263,
        "macd": -1.0,
        "bollinger": 0.8,
        "ma": -1.0,
        "volume": 0.1,
        "stochastic": 0.5
      },
      "timestamp": "2026-03-30T20:56:53.587160"
    },
    {
      "ticker": "PLTR",
      "sector": "NASDAQ_Tech",
      "signal": "HOLD",
      "confidence": 34,
      "composite_score": -0.146,
      "current_price": 137.55,
      "daily_change": -3.85,
      "buy_range": "$128.15 - $134.42",
      "sell_range": "$140.68 - $150.08",
      "support": 136.3,
      "resistance": 162.4,
      "indicators": {
        "rsi": 37.2,
        "macd_hist": -1.4188,
        "bb_position": -20.0,
        "vs_sma50": -7.17,
        "volume_ratio": 0.82,
        "stoch_k": 4.8
      },
      "individual_scores": {
        "rsi": 0.0,
        "macd": -1.0,
        "bollinger": 0.8,
        "ma": -1.0,
        "volume": -0.1,
        "stochastic": 0.5
      },
      "timestamp": "2026-03-30T20:56:53.823234"
    },
    {
      "ticker": "RGTI",
      "sector": "NASDAQ_Tech",
      "signal": "HOLD",
      "confidence": 28,
      "composite_score": -0.084,
      "current_price": 12.9,
      "daily_change": -3.15,
      "buy_range": "$11.31 - $12.37",
      "sell_range": "$13.43 - $15.01",
      "support": 12.53,
      "resistance": 17.96,
      "indicators": {
        "rsi": 18.3,
        "macd_hist": -0.2031,
        "bb_position": -7.6,
        "vs_sma50": -26.78,
        "volume_ratio": 0.94,
        "stoch_k": 7.5
      },
      "individual_scores": {
        "rsi": 0.78,
        "macd": -1.0,
        "bollinger": 0.8,
        "ma": -1.0,
        "volume": -0.1,
        "stochastic": 0.5
      },
      "timestamp": "2026-03-30T20:56:54.023146"
    },
    {
      "ticker": "SMCI",
      "sector": "NASDAQ_Tech",
      "signal": "HOLD",
      "confidence": 29,
      "composite_score": -0.096,
      "current_price": 21.06,
      "daily_change": -4.14,
      "buy_range": "$17.74 - $19.95",
      "sell_range": "$22.17 - $25.48",
      "support": 19.48,
      "resistance": 33.51,
      "indicators": {
        "rsi": 24.3,
        "macd_hist": -0.8906,
        "bb_position": 12.6,
        "vs_sma50": -30.25,
        "volume_ratio": 0.73,
        "stoch_k": 11.6
      },
      "individual_scores": {
        "rsi": 0.38,
        "macd": -0.5,
        "bollinger": 0.3,
        "ma": -1.0,
        "volume": -0.1,
        "stochastic": 0.5
      },
      "timestamp": "2026-03-30T20:56:54.166693"
    },
    {
      "ticker": "SNOW",
      "sector": "NASDAQ_Tech",
      "signal": "HOLD",
      "confidence": 34,
      "composite_score": -0.146,
      "current_price": 153.67,
      "daily_change": 0.57,
      "buy_range": "$141.87 - $149.74",
      "sell_range": "$157.6 - $169.4",
      "support": 150.6,
      "resistance": 184.74,
      "indicators": {
        "rsi": 30.3,
        "macd_hist": -1.6453,
        "bb_position": 1.3,
        "vs_sma50": -14.09,
        "volume_ratio": 0.7,
        "stoch_k": 9.0
      },
      "individual_scores": {
        "rsi": 0.0,
        "macd": -1.0,
        "bollinger": 0.8,
        "ma": -1.0,
        "volume": -0.1,
        "stochastic": 0.5
      },
      "timestamp": "2026-03-30T20:56:54.371356"
    },
    {
      "ticker": "STX",
      "sector": "NASDAQ_Tech",
      "signal": "HOLD",
      "confidence": 31,
      "composite_score": -0.118,
      "current_price": 362.43,
      "daily_change": -4.64,
      "buy_range": "$320.15 - $348.34",
      "sell_range": "$376.52 - $418.8",
      "support": 342.0,
      "resistance": 439.73,
      "indicators": {
        "rsi": 45.0,
        "macd_hist": -3.9296,
        "bb_position": 21.1,
        "vs_sma50": -8.51,
        "volume_ratio": 1.05,
        "stoch_k": 12.5
      },
      "individual_scores": {
        "rsi": 0.0,
        "macd": -1.0,
        "bollinger": 0.3,
        "ma": -0.4,
        "volume": 0.1,
        "stochastic": 0.0
      },
      "timestamp": "2026-03-30T20:56:54.650631"
    },
    {
      "ticker": "SYM",
      "sector": "NASDAQ_Tech",
      "signal": "HOLD",
      "confidence": 20,
      "composite_score": -0.006,
      "current_price": 47.41,
      "daily_change": -5.97,
      "buy_range": "$43.45 - $46.09",
      "sell_range": "$48.73 - $52.69",
      "support": 45.75,
      "resistance": 55.25,
      "indicators": {
        "rsi": 43.8,
        "macd_hist": 0.0538,
        "bb_position": -3.8,
        "vs_sma50": -13.68,
        "volume_ratio": 0.9,
        "stoch_k": 2.9
      },
      "individual_scores": {
        "rsi": 0.0,
        "macd": 0.5,
        "bollinger": 0.8,
        "ma": -1.0,
        "volume": -0.1,
        "stochastic": 0.0
      },
      "timestamp": "2026-03-30T20:56:54.752103"
    },
    {
      "ticker": "TSLA",
      "sector": "NASDAQ_Tech",
      "signal": "HOLD",
      "confidence": 33,
      "composite_score": -0.138,
      "current_price": 355.28,
      "daily_change": -1.81,
      "buy_range": "$335.52 - $348.69",
      "sell_range": "$361.87 - $381.63",
      "support": 352.14,
      "resistance": 416.38,
      "indicators": {
        "rsi": 30.6,
        "macd_hist": -2.4975,
        "bb_position": -5.8,
        "vs_sma50": -12.7,
        "volume_ratio": 1.05,
        "stoch_k": 4.9
      },
      "individual_scores": {
        "rsi": 0.0,
        "macd": -1.0,
        "bollinger": 0.8,
        "ma": -1.0,
        "volume": 0.1,
        "stochastic": 0.5
      },
      "timestamp": "2026-03-30T20:56:54.994319"
    },
    {
      "ticker": "WDC",
      "sector": "NASDAQ_Tech",
      "signal": "HOLD",
      "confidence": 32,
      "composite_score": -0.126,
      "current_price": 251.67,
      "daily_change": -8.6,
      "buy_range": "$218.5 - $240.61",
      "sell_range": "$262.73 - $295.89",
      "support": 238.0,
      "resistance": 319.62,
      "indicators": {
        "rsi": 45.7,
        "macd_hist": -4.0214,
        "bb_position": 20.0,
        "vs_sma50": -7.5,
        "volume_ratio": 0.98,
        "stoch_k": 3.7
      },
      "individual_scores": {
        "rsi": 0.0,
        "macd": -1.0,
        "bollinger": 0.3,
        "ma": -0.4,
        "volume": -0.1,
        "stochastic": 0.0
      },
      "timestamp": "2026-03-30T20:56:55.361671"
    },
    {
      "ticker": "COIN",
      "sector": "SP500_Broad",
      "signal": "HOLD",
      "confidence": 33,
      "composite_score": -0.136,
      "current_price": 160.79,
      "daily_change": -0.22,
      "buy_range": "$143.91 - $155.16",
      "sell_range": "$166.42 - $183.3",
      "support": 158.46,
      "resistance": 213.5,
      "indicators": {
        "rsi": 28.1,
        "macd_hist": -4.3776,
        "bb_position": -4.6,
        "vs_sma50": -14.17,
        "volume_ratio": 0.89,
        "stoch_k": 4.2
      },
      "individual_scores": {
        "rsi": 0.127,
        "macd": -1.0,
        "bollinger": 0.8,
        "ma": -1.0,
        "volume": -0.1,
        "stochastic": 0.5
      },
      "timestamp": "2026-03-30T20:56:55.456170"
    },
    {
      "ticker": "HOOD",
      "sector": "SP500_Broad",
      "signal": "HOLD",
      "confidence": 34,
      "composite_score": -0.14,
      "current_price": 65.16,
      "daily_change": -1.3,
      "buy_range": "$59.69 - $63.34",
      "sell_range": "$66.98 - $72.45",
      "support": 63.52,
      "resistance": 84.75,
      "indicators": {
        "rsi": 28.9,
        "macd_hist": -0.3593,
        "bb_position": -0.8,
        "vs_sma50": -20.73,
        "volume_ratio": 0.95,
        "stoch_k": 10.1
      },
      "individual_scores": {
        "rsi": 0.071,
        "macd": -1.0,
        "bollinger": 0.8,
        "ma": -1.0,
        "volume": -0.1,
        "stochastic": 0.5
      },
      "timestamp": "2026-03-30T20:56:55.556533"
    },
    {
      "ticker": "ISRG",
      "sector": "SP500_Broad",
      "signal": "HOLD",
      "confidence": 32,
      "composite_score": -0.126,
      "current_price": 452.77,
      "daily_change": 0.03,
      "buy_range": "$432.81 - $446.12",
      "sell_range": "$459.43 - $479.4",
      "support": 450.27,
      "resistance": 505.44,
      "indicators": {
        "rsi": 27.8,
        "macd_hist": -2.0942,
        "bb_position": -1.4,
        "vs_sma50": -8.32,
        "volume_ratio": 1.31,
        "stoch_k": 5.7
      },
      "individual_scores": {
        "rsi": 0.147,
        "macd": -1.0,
        "bollinger": 0.8,
        "ma": -1.0,
        "volume": 0.1,
        "stochastic": 0.5
      },
      "timestamp": "2026-03-30T20:56:55.671863"
    },
    {
      "ticker": "SOFI",
      "sector": "SP500_Broad",
      "signal": "HOLD",
      "confidence": 26,
      "composite_score": -0.066,
      "current_price": 15.15,
      "daily_change": -0.53,
      "buy_range": "$13.94 - $14.75",
      "sell_range": "$15.55 - $16.76",
      "support": 14.94,
      "resistance": 19.48,
      "indicators": {
        "rsi": 13.0,
        "macd_hist": -0.086,
        "bb_position": 1.2,
        "vs_sma50": -24.04,
        "volume_ratio": 0.87,
        "stoch_k": 5.4
      },
      "individual_scores": {
        "rsi": 1.0,
        "macd": -1.0,
        "bollinger": 0.8,
        "ma": -1.0,
        "volume": -0.1,
        "stochastic": 0.5
      },
      "timestamp": "2026-03-30T20:56:55.848829"
    },
    {
      "ticker": "BEAM",
      "sector": "Biotech",
      "signal": "HOLD",
      "confidence": 29,
      "composite_score": -0.098,
      "current_price": 21.9,
      "daily_change": -1.31,
      "buy_range": "$19.83 - $21.21",
      "sell_range": "$22.59 - $24.67",
      "support": 21.63,
      "resistance": 28.29,
      "indicators": {
        "rsi": 22.5,
        "macd_hist": -0.3162,
        "bb_position": -1.8,
        "vs_sma50": -19.85,
        "volume_ratio": 1.08,
        "stoch_k": 5.6
      },
      "individual_scores": {
        "rsi": 0.5,
        "macd": -1.0,
        "bollinger": 0.8,
        "ma": -1.0,
        "volume": 0.1,
        "stochastic": 0.5
      },
      "timestamp": "2026-03-30T20:56:55.951530"
    },
    {
      "ticker": "CRSP",
      "sector": "Biotech",
      "signal": "HOLD",
      "confidence": 33,
      "composite_score": -0.135,
      "current_price": 44.34,
      "daily_change": -3.08,
      "buy_range": "$41.16 - $43.28",
      "sell_range": "$45.4 - $48.58",
      "support": 44.12,
      "resistance": 60.6,
      "indicators": {
        "rsi": 22.4,
        "macd_hist": -0.4964,
        "bb_position": 19.2,
        "vs_sma50": -15.12,
        "volume_ratio": 0.7,
        "stoch_k": 2.8
      },
      "individual_scores": {
        "rsi": 0.507,
        "macd": -1.0,
        "bollinger": 0.3,
        "ma": -1.0,
        "volume": -0.1,
        "stochastic": 0.5
      },
      "timestamp": "2026-03-30T20:56:56.155033"
    },
    {
      "ticker": "DNA",
      "sector": "Biotech",
      "signal": "HOLD",
      "confidence": 33,
      "composite_score": -0.13,
      "current_price": 5.48,
      "daily_change": -7.59,
      "buy_range": "$4.68 - $5.21",
      "sell_range": "$5.75 - $6.54",
      "support": 5.37,
      "resistance": 7.65,
      "indicators": {
        "rsi": 41.3,
        "macd_hist": -0.0221,
        "bb_position": -20.0,
        "vs_sma50": -32.84,
        "volume_ratio": 1.69,
        "stoch_k": 4.8
      },
      "individual_scores": {
        "rsi": 0.0,
        "macd": -1.0,
        "bollinger": 0.8,
        "ma": -1.0,
        "volume": 0.3,
        "stochastic": 0.5
      },
      "timestamp": "2026-03-30T20:56:56.331986"
    },
    {
      "ticker": "RXRX",
      "sector": "Biotech",
      "signal": "HOLD",
      "confidence": 29,
      "composite_score": -0.091,
      "current_price": 2.84,
      "daily_change": -3.4,
      "buy_range": "$2.57 - $2.75",
      "sell_range": "$2.93 - $3.21",
      "support": 2.8,
      "resistance": 3.76,
      "indicators": {
        "rsi": 21.2,
        "macd_hist": -0.028,
        "bb_position": -10.3,
        "vs_sma50": -23.79,
        "volume_ratio": 1.18,
        "stoch_k": 5.3
      },
      "individual_scores": {
        "rsi": 0.59,
        "macd": -1.0,
        "bollinger": 0.8,
        "ma": -1.0,
        "volume": 0.1,
        "stochastic": 0.5
      },
      "timestamp": "2026-03-30T20:56:56.622897"
    },
    {
      "ticker": "ASTS",
      "sector": "Space",
      "signal": "HOLD",
      "confidence": 27,
      "composite_score": -0.078,
      "current_price": 73.82,
      "daily_change": -6.16,
      "buy_range": "$61.96 - $69.87",
      "sell_range": "$77.77 - $89.64",
      "support": 71.85,
      "resistance": 106.66,
      "indicators": {
        "rsi": 38.3,
        "macd_hist": -1.2788,
        "bb_position": -12.0,
        "vs_sma50": -22.14,
        "volume_ratio": 1.01,
        "stoch_k": 7.4
      },
      "individual_scores": {
        "rsi": 0.0,
        "macd": -1.0,
        "bollinger": 0.8,
        "ma": -0.4,
        "volume": 0.1,
        "stochastic": 0.5
      },
      "timestamp": "2026-03-30T20:56:56.959244"
    },
    {
      "ticker": "IRDM",
      "sector": "Space",
      "signal": "HOLD",
      "confidence": 34,
      "composite_score": 0.146,
      "current_price": 26.81,
      "daily_change": -4.11,
      "buy_range": "$24.6 - $26.07",
      "sell_range": "$27.55 - $29.76",
      "support": 23.25,
      "resistance": 30.25,
      "indicators": {
        "rsi": 59.5,
        "macd_hist": 0.0896,
        "bb_position": 67.7,
        "vs_sma50": 16.37,
        "volume_ratio": 0.91,
        "stoch_k": 43.8
      },
      "individual_scores": {
        "rsi": 0.0,
        "macd": 0.5,
        "bollinger": 0.0,
        "ma": 1.0,
        "volume": -0.1,
        "stochastic": 0.0
      },
      "timestamp": "2026-03-30T20:56:57.217189"
    },
    {
      "ticker": "RKLB",
      "sector": "Space",
      "signal": "HOLD",
      "confidence": 28,
      "composite_score": -0.086,
      "current_price": 57.38,
      "daily_change": -5.83,
      "buy_range": "$48.69 - $54.48",
      "sell_range": "$60.28 - $68.97",
      "support": 56.13,
      "resistance": 78.67,
      "indicators": {
        "rsi": 40.1,
        "macd_hist": -1.0513,
        "bb_position": -16.0,
        "vs_sma50": -22.16,
        "volume_ratio": 0.94,
        "stoch_k": 5.5
      },
      "individual_scores": {
        "rsi": 0.0,
        "macd": -1.0,
        "bollinger": 0.8,
        "ma": -0.4,
        "volume": -0.1,
        "stochastic": 0.5
      },
      "timestamp": "2026-03-30T20:56:57.321304"
    },
    {
      "ticker": "ENPH",
      "sector": "CleanEnergy",
      "signal": "HOLD",
      "confidence": 33,
      "composite_score": -0.138,
      "current_price": 35.64,
      "daily_change": -5.81,
      "buy_range": "$31.69 - $34.32",
      "sell_range": "$36.96 - $40.91",
      "support": 35.21,
      "resistance": 46.87,
      "indicators": {
        "rsi": 30.9,
        "macd_hist": -0.8466,
        "bb_position": -15.7,
        "vs_sma50": -16.82,
        "volume_ratio": 1.09,
        "stoch_k": 3.7
      },
      "individual_scores": {
        "rsi": 0.0,
        "macd": -1.0,
        "bollinger": 0.8,
        "ma": -1.0,
        "volume": 0.1,
        "stochastic": 0.5
      },
      "timestamp": "2026-03-30T20:56:57.422724"
    },
    {
      "ticker": "FSLR",
      "sector": "CleanEnergy",
      "signal": "HOLD",
      "confidence": 20,
      "composite_score": 0.004,
      "current_price": 184.7,
      "daily_change": -2.94,
      "buy_range": "$173.71 - $181.03",
      "sell_range": "$188.36 - $199.36",
      "support": 182.99,
      "resistance": 203.46,
      "indicators": {
        "rsi": 35.9,
        "macd_hist": 0.3109,
        "bb_position": -2.0,
        "vs_sma50": -14.44,
        "volume_ratio": 0.94,
        "stoch_k": 8.5
      },
      "individual_scores": {
        "rsi": 0.0,
        "macd": 0.5,
        "bollinger": 0.8,
        "ma": -1.0,
        "volume": -0.1,
        "stochastic": 0.5
      },
      "timestamp": "2026-03-30T20:56:57.536170"
    },
    {
      "ticker": "QS",
      "sector": "CleanEnergy",
      "signal": "HOLD",
      "confidence": 21,
      "composite_score": 0.012,
      "current_price": 5.96,
      "daily_change": -4.79,
      "buy_range": "$5.44 - $5.79",
      "sell_range": "$6.13 - $6.66",
      "support": 5.91,
      "resistance": 7.14,
      "indicators": {
        "rsi": 34.8,
        "macd_hist": 0.0088,
        "bb_position": -23.3,
        "vs_sma50": -23.94,
        "volume_ratio": 1.07,
        "stoch_k": 3.7
      },
      "individual_scores": {
        "rsi": 0.0,
        "macd": 0.5,
        "bollinger": 0.8,
        "ma": -1.0,
        "volume": 0.1,
        "stochastic": 0.5
      },
      "timestamp": "2026-03-30T20:56:57.697007"
    },
    {
      "ticker": "LEU",
      "sector": "Nuclear",
      "signal": "HOLD",
      "confidence": 33,
      "composite_score": -0.138,
      "current_price": 168.52,
      "daily_change": -7.86,
      "buy_range": "$148.52 - $161.85",
      "sell_range": "$175.19 - $195.19",
      "support": 165.91,
      "resistance": 227.37,
      "indicators": {
        "rsi": 31.5,
        "macd_hist": -0.9881,
        "bb_position": -14.5,
        "vs_sma50": -26.84,
        "volume_ratio": 1.27,
        "stoch_k": 4.2
      },
      "individual_scores": {
        "rsi": 0.0,
        "macd": -1.0,
        "bollinger": 0.8,
        "ma": -1.0,
        "volume": 0.1,
        "stochastic": 0.5
      },
      "timestamp": "2026-03-30T20:56:57.872210"
    }
  ],
  "summary": {
    "strong_buy": [],
    "buy": [],
    "hold": [
      "AMD",
      "AMZN",
      "ANET",
      "GOOG",
      "GOOGL",
      "IONQ",
      "META",
      "MU",
      "NET",
      "NVDA",
      "PLTR",
      "RGTI",
      "SMCI",
      "SNOW",
      "STX",
      "SYM",
      "TSLA",
      "WDC",
      "COIN",
      "HOOD",
      "ISRG",
      "SOFI",
      "BEAM",
      "CRSP",
      "DNA",
      "RXRX",
      "ASTS",
      "IRDM",
      "RKLB",
      "ENPH",
      "FSLR",
      "QS",
      "LEU"
    ],
    "sell": [],
    "strong_sell": []
  },
  "generated_at": "2026-03-30T20:56:52.044949",
  "options": [
    {
      "ticker": "AMD",
      "current_price": 196.04,
      "signal": "HOLD",
      "target_price": 214.57,
      "recommendation": "$200.0 CALL exp 2027-01-15 \u2192 Target $214.57",
      "options": [
        {
          "strike": 200.0,
          "bid": 40.65,
          "ask": 41.1,
          "mid_price": 40.88,
          "last_price": 40.79,
          "volume": 192,
          "open_interest": 10387,
          "implied_volatility": 61.4,
          "delta": 0.45,
          "intrinsic": 0,
          "extrinsic": 40.88,
          "moneyness": -2.0,
          "moneyness_label": "OTM",
          "break_even": 240.88,
          "target_price": 214.57,
          "return_at_target": -64.4,
          "max_loss": -100,
          "leverage": 2.2,
          "daily_theta_pct": 0.345,
          "liquidity_score": 100,
          "risk_reward": 0,
          "expiry": "2027-01-15",
          "days_to_expiry": 290,
          "option_type": "CALL",
          "score": 36
        }
      ]
    },
    {
      "ticker": "AMZN",
      "current_price": 200.95,
      "signal": "HOLD",
      "target_price": 211.48,
      "recommendation": "$220.0 CALL exp 2027-01-15 \u2192 Target $211.48",
      "options": [
        {
          "strike": 220.0,
          "bid": 21.85,
          "ask": 22.05,
          "mid_price": 21.95,
          "last_price": 22.03,
          "volume": 320,
          "open_interest": 7730,
          "implied_volatility": 41.0,
          "delta": 0.45,
          "intrinsic": 0,
          "extrinsic": 21.95,
          "moneyness": -9.5,
          "moneyness_label": "OTM",
          "break_even": 241.95,
          "target_price": 211.48,
          "return_at_target": -100.0,
          "max_loss": -100,
          "leverage": 4.1,
          "daily_theta_pct": 0.345,
          "liquidity_score": 100,
          "risk_reward": 0,
          "expiry": "2027-01-15",
          "days_to_expiry": 290,
          "option_type": "CALL",
          "score": 48
        }
      ]
    },
    {
      "ticker": "ANET",
      "current_price": 116.13,
      "signal": "HOLD",
      "target_price": 127.8,
      "recommendation": "$120.0 CALL exp 2027-01-15 \u2192 Target $127.80",
      "options": [
        {
          "strike": 120.0,
          "bid": 21.85,
          "ask": 24.0,
          "mid_price": 22.93,
          "last_price": 22.58,
          "volume": 10,
          "open_interest": 694,
          "implied_volatility": 59.6,
          "delta": 0.45,
          "intrinsic": 0,
          "extrinsic": 22.93,
          "moneyness": -3.3,
          "moneyness_label": "OTM",
          "break_even": 142.93,
          "target_price": 127.8,
          "return_at_target": -66.0,
          "max_loss": -100,
          "leverage": 2.3,
          "daily_theta_pct": 0.345,
          "liquidity_score": 7.9,
          "risk_reward": 0,
          "expiry": "2027-01-15",
          "days_to_expiry": 290,
          "option_type": "CALL",
          "score": 32
        }
      ]
    },
    {
      "ticker": "GOOG",
      "current_price": 273.14,
      "signal": "HOLD",
      "target_price": 286.78,
      "recommendation": "$290.0 CALL exp 2027-01-15 \u2192 Target $286.78",
      "options": [
        {
          "strike": 290.0,
          "bid": 30.2,
          "ask": 30.9,
          "mid_price": 30.55,
          "last_price": 30.2,
          "volume": 233,
          "open_interest": 6557,
          "implied_volatility": 38.8,
          "delta": 0.45,
          "intrinsic": 0,
          "extrinsic": 30.55,
          "moneyness": -6.2,
          "moneyness_label": "OTM",
          "break_even": 320.55,
          "target_price": 286.78,
          "return_at_target": -100.0,
          "max_loss": -100,
          "leverage": 4.0,
          "daily_theta_pct": 0.345,
          "liquidity_score": 88.9,
          "risk_reward": 0,
          "expiry": "2027-01-15",
          "days_to_expiry": 290,
          "option_type": "CALL",
          "score": 48
        }
      ]
    },
    {
      "ticker": "GOOGL",
      "current_price": 273.5,
      "signal": "HOLD",
      "target_price": 287.62,
      "recommendation": "$55.0 CALL exp 2027-06-17 \u2192 Target $287.62",
      "options": [
        {
          "strike": 55.0,
          "bid": 0,
          "ask": 0,
          "mid_price": 97.23,
          "last_price": 97.23,
          "volume": 0,
          "open_interest": 0,
          "implied_volatility": 0.0,
          "delta": 0.8,
          "intrinsic": 218.5,
          "extrinsic": -121.27,
          "moneyness": 79.9,
          "moneyness_label": "ITM",
          "break_even": 152.23,
          "target_price": 287.62,
          "return_at_target": 139.2,
          "max_loss": -100,
          "leverage": 2.3,
          "daily_theta_pct": -0.282,
          "liquidity_score": 0.0,
          "risk_reward": 1.39,
          "expiry": "2027-06-17",
          "days_to_expiry": 443,
          "option_type": "CALL",
          "score": 54.8
        }
      ]
    },
    {
      "ticker": "IONQ",
      "current_price": 26.59,
      "signal": "HOLD",
      "target_price": 30.54,
      "recommendation": "$25.0 CALL exp 2027-01-15 \u2192 Target $30.54",
      "options": [
        {
          "strike": 25.0,
          "bid": 8.45,
          "ask": 9.2,
          "mid_price": 8.82,
          "last_price": 8.75,
          "volume": 25,
          "open_interest": 1993,
          "implied_volatility": 89.3,
          "delta": 0.55,
          "intrinsic": 1.59,
          "extrinsic": 7.24,
          "moneyness": 6.0,
          "moneyness_label": "ITM",
          "break_even": 33.83,
          "target_price": 30.54,
          "return_at_target": -37.2,
          "max_loss": -100,
          "leverage": 1.7,
          "daily_theta_pct": 0.283,
          "liquidity_score": 22.4,
          "risk_reward": 0,
          "expiry": "2027-01-15",
          "days_to_expiry": 290,
          "option_type": "CALL",
          "score": 28
        }
      ]
    },
    {
      "ticker": "META",
      "current_price": 536.38,
      "signal": "HOLD",
      "target_price": 574.39,
      "recommendation": "$550.0 CALL exp 2027-01-15 \u2192 Target $574.39",
      "options": [
        {
          "strike": 550.0,
          "bid": 78.35,
          "ask": 78.9,
          "mid_price": 78.62,
          "last_price": 78.55,
          "volume": 158,
          "open_interest": 1148,
          "implied_volatility": 44.4,
          "delta": 0.45,
          "intrinsic": 0,
          "extrinsic": 78.62,
          "moneyness": -2.5,
          "moneyness_label": "OTM",
          "break_even": 628.62,
          "target_price": 574.39,
          "return_at_target": -69.0,
          "max_loss": -100,
          "leverage": 3.1,
          "daily_theta_pct": 0.345,
          "liquidity_score": 27.3,
          "risk_reward": 0,
          "expiry": "2027-01-15",
          "days_to_expiry": 290,
          "option_type": "CALL",
          "score": 41
        }
      ]
    },
    {
      "ticker": "MU",
      "current_price": 321.8,
      "signal": "HOLD",
      "target_price": 375.63,
      "recommendation": "$47.5 CALL exp 2026-12-18 \u2192 Target $375.63",
      "options": [
        {
          "strike": 47.5,
          "bid": 135.0,
          "ask": 139.5,
          "mid_price": 137.25,
          "last_price": 112.0,
          "volume": 1,
          "open_interest": 168,
          "implied_volatility": 0.0,
          "delta": 0.8,
          "intrinsic": 274.3,
          "extrinsic": -137.05,
          "moneyness": 85.2,
          "moneyness_label": "ITM",
          "break_even": 184.75,
          "target_price": 375.63,
          "return_at_target": 139.1,
          "max_loss": -100,
          "leverage": 1.9,
          "daily_theta_pct": -0.381,
          "liquidity_score": 1.8,
          "risk_reward": 1.39,
          "expiry": "2026-12-18",
          "days_to_expiry": 262,
          "option_type": "CALL",
          "score": 49.8
        }
      ]
    },
    {
      "ticker": "NET",
      "current_price": 194.63,
      "signal": "HOLD",
      "target_price": 216.28,
      "recommendation": "$77.5 CALL exp 2027-01-15 \u2192 Target $216.28",
      "options": [
        {
          "strike": 77.5,
          "bid": 63.1,
          "ask": 64.8,
          "mid_price": 63.95,
          "last_price": 40.74,
          "volume": 2,
          "open_interest": 4,
          "implied_volatility": 0.0,
          "delta": 0.8,
          "intrinsic": 117.13,
          "extrinsic": -53.18,
          "moneyness": 60.2,
          "moneyness_label": "ITM",
          "break_even": 141.45,
          "target_price": 216.28,
          "return_at_target": 117.0,
          "max_loss": -100,
          "leverage": 2.4,
          "daily_theta_pct": -0.287,
          "liquidity_score": 0.2,
          "risk_reward": 1.17,
          "expiry": "2027-01-15",
          "days_to_expiry": 290,
          "option_type": "CALL",
          "score": 49.2
        }
      ]
    },
    {
      "ticker": "NVDA",
      "current_price": 165.17,
      "signal": "HOLD",
      "target_price": 175.36,
      "recommendation": "$165.0 CALL exp 2027-01-15 \u2192 Target $175.36",
      "options": [
        {
          "strike": 165.0,
          "bid": 28.5,
          "ask": 28.65,
          "mid_price": 28.57,
          "last_price": 28.65,
          "volume": 470,
          "open_interest": 7491,
          "implied_volatility": 48.9,
          "delta": 0.55,
          "intrinsic": 0.17,
          "extrinsic": 28.41,
          "moneyness": 0.1,
          "moneyness_label": "ATM",
          "break_even": 193.57,
          "target_price": 175.36,
          "return_at_target": -63.7,
          "max_loss": -100,
          "leverage": 3.2,
          "daily_theta_pct": 0.343,
          "liquidity_score": 100,
          "risk_reward": 0,
          "expiry": "2027-01-15",
          "days_to_expiry": 290,
          "option_type": "CALL",
          "score": 43
        }
      ]
    },
    {
      "ticker": "PLTR",
      "current_price": 137.55,
      "signal": "HOLD",
      "target_price": 150.08,
      "recommendation": "$150.0 CALL exp 2027-01-15 \u2192 Target $150.08",
      "options": [
        {
          "strike": 150.0,
          "bid": 24.8,
          "ask": 25.15,
          "mid_price": 24.98,
          "last_price": 25.0,
          "volume": 93,
          "open_interest": 9346,
          "implied_volatility": 60.8,
          "delta": 0.45,
          "intrinsic": 0,
          "extrinsic": 24.98,
          "moneyness": -9.1,
          "moneyness_label": "OTM",
          "break_even": 174.97,
          "target_price": 150.08,
          "return_at_target": -99.7,
          "max_loss": -100,
          "leverage": 2.5,
          "daily_theta_pct": 0.345,
          "liquidity_score": 100,
          "risk_reward": 0,
          "expiry": "2027-01-15",
          "days_to_expiry": 290,
          "option_type": "CALL",
          "score": 36
        }
      ]
    },
    {
      "ticker": "RGTI",
      "current_price": 12.9,
      "signal": "HOLD",
      "target_price": 15.01,
      "recommendation": "$50.0 CALL exp 2027-01-15 \u2192 Target $15.01",
      "options": [
        {
          "strike": 50.0,
          "bid": 0.52,
          "ask": 0.55,
          "mid_price": 0.54,
          "last_price": 0.57,
          "volume": 9,
          "open_interest": 7912,
          "implied_volatility": 97.5,
          "delta": 0.2,
          "intrinsic": 0,
          "extrinsic": 0.54,
          "moneyness": -287.6,
          "moneyness_label": "OTM",
          "break_even": 50.53,
          "target_price": 15.01,
          "return_at_target": -100.0,
          "max_loss": -100,
          "leverage": 4.8,
          "daily_theta_pct": 0.345,
          "liquidity_score": 80.0,
          "risk_reward": 0,
          "expiry": "2027-01-15",
          "days_to_expiry": 290,
          "option_type": "CALL",
          "score": 30
        }
      ]
    },
    {
      "ticker": "SMCI",
      "current_price": 21.06,
      "signal": "HOLD",
      "target_price": 25.48,
      "recommendation": "$20.0 CALL exp 2027-01-15 \u2192 Target $25.48",
      "options": [
        {
          "strike": 20.0,
          "bid": 6.85,
          "ask": 7.15,
          "mid_price": 7.0,
          "last_price": 7.05,
          "volume": 37,
          "open_interest": 2585,
          "implied_volatility": 90.6,
          "delta": 0.55,
          "intrinsic": 1.06,
          "extrinsic": 5.94,
          "moneyness": 5.0,
          "moneyness_label": "ITM",
          "break_even": 27.0,
          "target_price": 25.48,
          "return_at_target": -21.7,
          "max_loss": -100,
          "leverage": 1.7,
          "daily_theta_pct": 0.293,
          "liquidity_score": 29.6,
          "risk_reward": 0,
          "expiry": "2027-01-15",
          "days_to_expiry": 290,
          "option_type": "CALL",
          "score": 33
        }
      ]
    },
    {
      "ticker": "SNOW",
      "current_price": 153.67,
      "signal": "HOLD",
      "target_price": 169.4,
      "recommendation": "$155.0 CALL exp 2027-09-17 \u2192 Target $169.40",
      "options": [
        {
          "strike": 155.0,
          "bid": 44.95,
          "ask": 47.5,
          "mid_price": 46.23,
          "last_price": 47.15,
          "volume": 10,
          "open_interest": 5066,
          "implied_volatility": 64.4,
          "delta": 0.45,
          "intrinsic": 0,
          "extrinsic": 46.23,
          "moneyness": -0.9,
          "moneyness_label": "ATM",
          "break_even": 201.22,
          "target_price": 169.4,
          "return_at_target": -68.8,
          "max_loss": -100,
          "leverage": 1.5,
          "daily_theta_pct": 0.187,
          "liquidity_score": 51.7,
          "risk_reward": 0,
          "expiry": "2027-09-17",
          "days_to_expiry": 535,
          "option_type": "CALL",
          "score": 36
        }
      ]
    },
    {
      "ticker": "STX",
      "current_price": 362.43,
      "signal": "HOLD",
      "target_price": 418.8,
      "recommendation": "$45.0 CALL exp 2027-01-15 \u2192 Target $418.80",
      "options": [
        {
          "strike": 45.0,
          "bid": 94.5,
          "ask": 98.6,
          "mid_price": 96.55,
          "last_price": 72.4,
          "volume": 1,
          "open_interest": 0,
          "implied_volatility": 0.0,
          "delta": 0.8,
          "intrinsic": 317.43,
          "extrinsic": -220.88,
          "moneyness": 87.6,
          "moneyness_label": "ITM",
          "break_even": 141.55,
          "target_price": 418.8,
          "return_at_target": 287.2,
          "max_loss": -100,
          "leverage": 3.0,
          "daily_theta_pct": -0.789,
          "liquidity_score": 0.1,
          "risk_reward": 2.87,
          "expiry": "2027-01-15",
          "days_to_expiry": 290,
          "option_type": "CALL",
          "score": 75
        }
      ]
    },
    {
      "ticker": "SYM",
      "current_price": 47.41,
      "signal": "HOLD",
      "target_price": 52.69,
      "recommendation": "$50.0 CALL exp 2027-01-15 \u2192 Target $52.69",
      "options": [
        {
          "strike": 50.0,
          "bid": 12.4,
          "ask": 14.2,
          "mid_price": 13.3,
          "last_price": 13.0,
          "volume": 1,
          "open_interest": 512,
          "implied_volatility": 85.8,
          "delta": 0.45,
          "intrinsic": 0,
          "extrinsic": 13.3,
          "moneyness": -5.5,
          "moneyness_label": "OTM",
          "break_even": 63.3,
          "target_price": 52.69,
          "return_at_target": -79.8,
          "max_loss": -100,
          "leverage": 1.6,
          "daily_theta_pct": 0.345,
          "liquidity_score": 5.2,
          "risk_reward": 0,
          "expiry": "2027-01-15",
          "days_to_expiry": 290,
          "option_type": "CALL",
          "score": 31
        }
      ]
    },
    {
      "ticker": "TSLA",
      "current_price": 355.28,
      "signal": "HOLD",
      "target_price": 381.63,
      "recommendation": "$390.0 CALL exp 2027-01-15 \u2192 Target $381.63",
      "options": [
        {
          "strike": 390.0,
          "bid": 52.85,
          "ask": 53.1,
          "mid_price": 52.98,
          "last_price": 51.6,
          "volume": 121,
          "open_interest": 2429,
          "implied_volatility": 52.4,
          "delta": 0.45,
          "intrinsic": 0,
          "extrinsic": 52.98,
          "moneyness": -9.8,
          "moneyness_label": "OTM",
          "break_even": 442.98,
          "target_price": 381.63,
          "return_at_target": -100.0,
          "max_loss": -100,
          "leverage": 3.0,
          "daily_theta_pct": 0.345,
          "liquidity_score": 36.4,
          "risk_reward": 0,
          "expiry": "2027-01-15",
          "days_to_expiry": 290,
          "option_type": "CALL",
          "score": 39
        }
      ]
    },
    {
      "ticker": "WDC",
      "current_price": 251.67,
      "signal": "HOLD",
      "target_price": 295.89,
      "recommendation": "$32.5 CALL exp 2027-01-15 \u2192 Target $295.89",
      "options": [
        {
          "strike": 32.5,
          "bid": 45.8,
          "ask": 46.9,
          "mid_price": 46.35,
          "last_price": 36.64,
          "volume": 2,
          "open_interest": 37,
          "implied_volatility": 0.0,
          "delta": 0.8,
          "intrinsic": 219.17,
          "extrinsic": -172.82,
          "moneyness": 87.1,
          "moneyness_label": "ITM",
          "break_even": 78.85,
          "target_price": 295.89,
          "return_at_target": 468.3,
          "max_loss": -100,
          "leverage": 4.3,
          "daily_theta_pct": -1.286,
          "liquidity_score": 0.6,
          "risk_reward": 4.68,
          "expiry": "2027-01-15",
          "days_to_expiry": 290,
          "option_type": "CALL",
          "score": 80
        }
      ]
    },
    {
      "ticker": "COIN",
      "current_price": 160.79,
      "signal": "HOLD",
      "target_price": 183.3,
      "recommendation": "$175.0 CALL exp 2027-01-15 \u2192 Target $183.30",
      "options": [
        {
          "strike": 175.0,
          "bid": 35.8,
          "ask": 41.3,
          "mid_price": 38.55,
          "last_price": 40.1,
          "volume": 10,
          "open_interest": 450,
          "implied_volatility": 77.2,
          "delta": 0.45,
          "intrinsic": 0,
          "extrinsic": 38.55,
          "moneyness": -8.8,
          "moneyness_label": "OTM",
          "break_even": 213.55,
          "target_price": 183.3,
          "return_at_target": -78.5,
          "max_loss": -100,
          "leverage": 1.9,
          "daily_theta_pct": 0.345,
          "liquidity_score": 5.5,
          "risk_reward": 0,
          "expiry": "2027-01-15",
          "days_to_expiry": 290,
          "option_type": "CALL",
          "score": 31
        }
      ]
    },
    {
      "ticker": "HOOD",
      "current_price": 65.16,
      "signal": "HOLD",
      "target_price": 72.45,
      "recommendation": "$70.0 CALL exp 2027-01-15 \u2192 Target $72.45",
      "options": [
        {
          "strike": 70.0,
          "bid": 14.5,
          "ask": 15.8,
          "mid_price": 15.15,
          "last_price": 14.83,
          "volume": 130,
          "open_interest": 5095,
          "implied_volatility": 73.8,
          "delta": 0.45,
          "intrinsic": 0,
          "extrinsic": 15.15,
          "moneyness": -7.4,
          "moneyness_label": "OTM",
          "break_even": 85.15,
          "target_price": 72.45,
          "return_at_target": -83.8,
          "max_loss": -100,
          "leverage": 1.9,
          "daily_theta_pct": 0.345,
          "liquidity_score": 64.0,
          "risk_reward": 0,
          "expiry": "2027-01-15",
          "days_to_expiry": 290,
          "option_type": "CALL",
          "score": 35
        }
      ]
    },
    {
      "ticker": "ISRG",
      "current_price": 452.77,
      "signal": "HOLD",
      "target_price": 479.4,
      "recommendation": "$490.0 CALL exp 2027-01-15 \u2192 Target $479.40",
      "options": [
        {
          "strike": 490.0,
          "bid": 46.3,
          "ask": 53.4,
          "mid_price": 49.85,
          "last_price": 66.0,
          "volume": 1,
          "open_interest": 155,
          "implied_volatility": 42.1,
          "delta": 0.45,
          "intrinsic": 0,
          "extrinsic": 49.85,
          "moneyness": -8.2,
          "moneyness_label": "OTM",
          "break_even": 539.85,
          "target_price": 479.4,
          "return_at_target": -100.0,
          "max_loss": -100,
          "leverage": 4.1,
          "daily_theta_pct": 0.345,
          "liquidity_score": 1.7,
          "risk_reward": 0,
          "expiry": "2027-01-15",
          "days_to_expiry": 290,
          "option_type": "CALL",
          "score": 43
        }
      ]
    },
    {
      "ticker": "SOFI",
      "current_price": 15.15,
      "signal": "HOLD",
      "target_price": 16.76,
      "recommendation": "$15.0 CALL exp 2027-01-15 \u2192 Target $16.76",
      "options": [
        {
          "strike": 15.0,
          "bid": 3.85,
          "ask": 3.95,
          "mid_price": 3.9,
          "last_price": 3.9,
          "volume": 3153,
          "open_interest": 33206,
          "implied_volatility": 72.3,
          "delta": 0.55,
          "intrinsic": 0.15,
          "extrinsic": 3.75,
          "moneyness": 1.0,
          "moneyness_label": "ATM",
          "break_even": 18.9,
          "target_price": 16.76,
          "return_at_target": -54.9,
          "max_loss": -100,
          "leverage": 2.1,
          "daily_theta_pct": 0.332,
          "liquidity_score": 100,
          "risk_reward": 0,
          "expiry": "2027-01-15",
          "days_to_expiry": 290,
          "option_type": "CALL",
          "score": 35
        }
      ]
    },
    {
      "ticker": "BEAM",
      "current_price": 21.9,
      "signal": "HOLD",
      "target_price": 24.67,
      "recommendation": "$22.0 CALL exp 2027-01-15 \u2192 Target $24.67",
      "options": [
        {
          "strike": 22.0,
          "bid": 4.2,
          "ask": 8.0,
          "mid_price": 6.1,
          "last_price": 8.54,
          "volume": 6,
          "open_interest": 31,
          "implied_volatility": 80.2,
          "delta": 0.45,
          "intrinsic": 0,
          "extrinsic": 6.1,
          "moneyness": -0.5,
          "moneyness_label": "ATM",
          "break_even": 28.1,
          "target_price": 24.67,
          "return_at_target": -56.2,
          "max_loss": -100,
          "leverage": 1.6,
          "daily_theta_pct": 0.345,
          "liquidity_score": 0.9,
          "risk_reward": 0,
          "expiry": "2027-01-15",
          "days_to_expiry": 290,
          "option_type": "CALL",
          "score": 30
        }
      ]
    },
    {
      "ticker": "CRSP",
      "current_price": 44.34,
      "signal": "HOLD",
      "target_price": 48.58,
      "recommendation": "$42.5 CALL exp 2027-01-15 \u2192 Target $48.58",
      "options": [
        {
          "strike": 42.5,
          "bid": 10.3,
          "ask": 12.5,
          "mid_price": 11.4,
          "last_price": 13.1,
          "volume": 2,
          "open_interest": 66,
          "implied_volatility": 68.5,
          "delta": 0.55,
          "intrinsic": 1.84,
          "extrinsic": 9.56,
          "moneyness": 4.1,
          "moneyness_label": "ITM",
          "break_even": 53.9,
          "target_price": 48.58,
          "return_at_target": -46.7,
          "max_loss": -100,
          "leverage": 2.1,
          "daily_theta_pct": 0.289,
          "liquidity_score": 0.9,
          "risk_reward": 0,
          "expiry": "2027-01-15",
          "days_to_expiry": 290,
          "option_type": "CALL",
          "score": 31
        }
      ]
    },
    {
      "ticker": "DNA",
      "current_price": 5.48,
      "signal": "HOLD",
      "target_price": 6.54,
      "recommendation": "$5.0 CALL exp 2027-01-15 \u2192 Target $6.54",
      "options": [
        {
          "strike": 5.0,
          "bid": 1.2,
          "ask": 2.5,
          "mid_price": 1.85,
          "last_price": 2.2,
          "volume": 1,
          "open_interest": 180,
          "implied_volatility": 87.7,
          "delta": 0.55,
          "intrinsic": 0.48,
          "extrinsic": 1.37,
          "moneyness": 8.8,
          "moneyness_label": "ITM",
          "break_even": 6.85,
          "target_price": 6.54,
          "return_at_target": -16.8,
          "max_loss": -100,
          "leverage": 1.6,
          "daily_theta_pct": 0.255,
          "liquidity_score": 1.9,
          "risk_reward": 0,
          "expiry": "2027-01-15",
          "days_to_expiry": 290,
          "option_type": "CALL",
          "score": 25
        }
      ]
    },
    {
      "ticker": "RXRX",
      "current_price": 2.84,
      "signal": "HOLD",
      "target_price": 3.21,
      "recommendation": "$3.0 CALL exp 2027-01-15 \u2192 Target $3.21",
      "options": [
        {
          "strike": 3.0,
          "bid": 0.8,
          "ask": 0.95,
          "mid_price": 0.88,
          "last_price": 0.92,
          "volume": 41,
          "open_interest": 10220,
          "implied_volatility": 94.1,
          "delta": 0.45,
          "intrinsic": 0,
          "extrinsic": 0.88,
          "moneyness": -5.6,
          "moneyness_label": "OTM",
          "break_even": 3.88,
          "target_price": 3.21,
          "return_at_target": -76.0,
          "max_loss": -100,
          "leverage": 1.5,
          "daily_theta_pct": 0.345,
          "liquidity_score": 100,
          "risk_reward": 0,
          "expiry": "2027-01-15",
          "days_to_expiry": 290,
          "option_type": "CALL",
          "score": 35
        }
      ]
    },
    {
      "ticker": "ASTS",
      "current_price": 73.82,
      "signal": "HOLD",
      "target_price": 89.64,
      "recommendation": "$75.0 CALL exp 2027-01-15 \u2192 Target $89.64",
      "options": [
        {
          "strike": 75.0,
          "bid": 25.05,
          "ask": 26.5,
          "mid_price": 25.77,
          "last_price": 25.78,
          "volume": 24,
          "open_interest": 1983,
          "implied_volatility": 102.8,
          "delta": 0.45,
          "intrinsic": 0,
          "extrinsic": 25.77,
          "moneyness": -1.6,
          "moneyness_label": "ATM",
          "break_even": 100.78,
          "target_price": 89.64,
          "return_at_target": -43.2,
          "max_loss": -100,
          "leverage": 1.3,
          "daily_theta_pct": 0.345,
          "liquidity_score": 22.2,
          "risk_reward": 0,
          "expiry": "2027-01-15",
          "days_to_expiry": 290,
          "option_type": "CALL",
          "score": 33
        }
      ]
    },
    {
      "ticker": "IRDM",
      "current_price": 26.81,
      "signal": "HOLD",
      "target_price": 29.76,
      "recommendation": "$30.0 CALL exp 2026-10-16 \u2192 Target $29.76",
      "options": [
        {
          "strike": 30.0,
          "bid": 3.2,
          "ask": 4.6,
          "mid_price": 3.9,
          "last_price": 3.4,
          "volume": 111,
          "open_interest": 913,
          "implied_volatility": 64.2,
          "delta": 0.2,
          "intrinsic": 0,
          "extrinsic": 3.9,
          "moneyness": -11.9,
          "moneyness_label": "OTM",
          "break_even": 33.9,
          "target_price": 29.76,
          "return_at_target": -100.0,
          "max_loss": -100,
          "leverage": 1.4,
          "daily_theta_pct": 0.503,
          "liquidity_score": 20.2,
          "risk_reward": 0,
          "expiry": "2026-10-16",
          "days_to_expiry": 199,
          "option_type": "CALL",
          "score": 24
        }
      ]
    },
    {
      "ticker": "RKLB",
      "current_price": 57.38,
      "signal": "HOLD",
      "target_price": 68.97,
      "recommendation": "$60.0 CALL exp 2027-01-15 \u2192 Target $68.97",
      "options": [
        {
          "strike": 60.0,
          "bid": 16.8,
          "ask": 17.3,
          "mid_price": 17.05,
          "last_price": 16.75,
          "volume": 280,
          "open_interest": 3455,
          "implied_volatility": 89.9,
          "delta": 0.45,
          "intrinsic": 0,
          "extrinsic": 17.05,
          "moneyness": -4.6,
          "moneyness_label": "OTM",
          "break_even": 77.05,
          "target_price": 68.97,
          "return_at_target": -47.4,
          "max_loss": -100,
          "leverage": 1.5,
          "daily_theta_pct": 0.345,
          "liquidity_score": 62.5,
          "risk_reward": 0,
          "expiry": "2027-01-15",
          "days_to_expiry": 290,
          "option_type": "CALL",
          "score": 35
        }
      ]
    },
    {
      "ticker": "ENPH",
      "current_price": 35.64,
      "signal": "HOLD",
      "target_price": 40.91,
      "recommendation": "$35.0 CALL exp 2027-01-15 \u2192 Target $40.91",
      "options": [
        {
          "strike": 35.0,
          "bid": 9.3,
          "ask": 10.55,
          "mid_price": 9.93,
          "last_price": 9.6,
          "volume": 11,
          "open_interest": 2769,
          "implied_volatility": 77.7,
          "delta": 0.55,
          "intrinsic": 0.64,
          "extrinsic": 9.28,
          "moneyness": 1.8,
          "moneyness_label": "ATM",
          "break_even": 44.92,
          "target_price": 40.91,
          "return_at_target": -40.5,
          "max_loss": -100,
          "leverage": 2.0,
          "daily_theta_pct": 0.323,
          "liquidity_score": 28.8,
          "risk_reward": 0,
          "expiry": "2027-01-15",
          "days_to_expiry": 290,
          "option_type": "CALL",
          "score": 33
        }
      ]
    },
    {
      "ticker": "FSLR",
      "current_price": 184.7,
      "signal": "HOLD",
      "target_price": 199.36,
      "recommendation": "$180.0 CALL exp 2027-01-15 \u2192 Target $199.36",
      "options": [
        {
          "strike": 180.0,
          "bid": 40.1,
          "ask": 43.0,
          "mid_price": 41.55,
          "last_price": 42.9,
          "volume": 12,
          "open_interest": 407,
          "implied_volatility": 60.9,
          "delta": 0.55,
          "intrinsic": 4.7,
          "extrinsic": 36.85,
          "moneyness": 2.5,
          "moneyness_label": "ITM",
          "break_even": 221.55,
          "target_price": 199.36,
          "return_at_target": -53.4,
          "max_loss": -100,
          "leverage": 2.4,
          "daily_theta_pct": 0.306,
          "liquidity_score": 5.3,
          "risk_reward": 0,
          "expiry": "2027-01-15",
          "days_to_expiry": 290,
          "option_type": "CALL",
          "score": 32
        }
      ]
    },
    {
      "ticker": "QS",
      "current_price": 5.96,
      "signal": "HOLD",
      "target_price": 6.66,
      "recommendation": "$22.0 CALL exp 2027-01-15 \u2192 Target $6.66",
      "options": [
        {
          "strike": 22.0,
          "bid": 0.25,
          "ask": 0.27,
          "mid_price": 0.26,
          "last_price": 0.28,
          "volume": 202,
          "open_interest": 6465,
          "implied_volatility": 96.3,
          "delta": 0.2,
          "intrinsic": 0,
          "extrinsic": 0.26,
          "moneyness": -269.1,
          "moneyness_label": "OTM",
          "break_even": 22.26,
          "target_price": 6.66,
          "return_at_target": -100.0,
          "max_loss": -100,
          "leverage": 4.6,
          "daily_theta_pct": 0.345,
          "liquidity_score": 84.9,
          "risk_reward": 0,
          "expiry": "2027-01-15",
          "days_to_expiry": 290,
          "option_type": "CALL",
          "score": 30
        }
      ]
    },
    {
      "ticker": "LEU",
      "current_price": 168.52,
      "signal": "HOLD",
      "target_price": 195.19,
      "recommendation": "$165.0 CALL exp 2027-01-15 \u2192 Target $195.19",
      "options": [
        {
          "strike": 165.0,
          "bid": 50.3,
          "ask": 53.6,
          "mid_price": 51.95,
          "last_price": 82.5,
          "volume": 2,
          "open_interest": 3,
          "implied_volatility": 86.4,
          "delta": 0.55,
          "intrinsic": 3.52,
          "extrinsic": 48.43,
          "moneyness": 2.1,
          "moneyness_label": "ITM",
          "break_even": 216.95,
          "target_price": 195.19,
          "return_at_target": -41.9,
          "max_loss": -100,
          "leverage": 1.8,
          "daily_theta_pct": 0.321,
          "liquidity_score": 0.2,
          "risk_reward": 0,
          "expiry": "2027-01-15",
          "days_to_expiry": 290,
          "option_type": "CALL",
          "score": 30
        }
      ]
    }
  ]
}