{
  "market_regime": {
    "regime": "NEUTRAL",
    "details": {
      "spy_price": 684.87,
      "spy_vs_50ma": -0.13,
      "spy_vs_200ma": 6.62,
      "qqq_price": 601.96,
      "qqq_vs_50ma": -2.74,
      "vix": 19.1
    },
    "modifier": 0.7
  },
  "signals": [
    {
      "ticker": "AMD",
      "sector": "NASDAQ_Tech",
      "signal": "SELL",
      "confidence": 40,
      "composite_score": -0.203,
      "current_price": 204.52,
      "daily_change": 6.25,
      "buy_range": "$180.95 - $196.67",
      "sell_range": "$212.38 - $235.95",
      "support": 190.72,
      "resistance": 266.96,
      "indicators": {
        "rsi": 39.4,
        "macd_hist": -5.9574,
        "bb_position": 17.4,
        "vs_sma50": -7.62,
        "volume_ratio": 0.39,
        "stoch_k": 18.1
      },
      "individual_scores": {
        "rsi": 0.0,
        "macd": -1.0,
        "bollinger": 0.3,
        "ma": -0.4,
        "volume": -0.1,
        "stochastic": 0.5
      },
      "timestamp": "2026-02-06T15:11:06.096190"
    },
    {
      "ticker": "AMZN",
      "sector": "NASDAQ_Tech",
      "signal": "HOLD",
      "confidence": 39,
      "composite_score": -0.193,
      "current_price": 202.32,
      "daily_change": -9.15,
      "buy_range": "$190.01 - $198.22",
      "sell_range": "$206.42 - $218.74",
      "support": 200.31,
      "resistance": 248.94,
      "indicators": {
        "rsi": 24.8,
        "macd_hist": -3.4292,
        "bb_position": -35.8,
        "vs_sma50": -13.22,
        "volume_ratio": 1.14,
        "stoch_k": 4.2
      },
      "individual_scores": {
        "rsi": 0.348,
        "macd": -1.0,
        "bollinger": 0.8,
        "ma": -1.0,
        "volume": 0.1,
        "stochastic": 0.5
      },
      "timestamp": "2026-02-06T15:11:06.408202"
    },
    {
      "ticker": "ANET",
      "sector": "NASDAQ_Tech",
      "signal": "HOLD",
      "confidence": 27,
      "composite_score": -0.07,
      "current_price": 132.95,
      "daily_change": 3.33,
      "buy_range": "$122.18 - $129.36",
      "sell_range": "$136.54 - $147.31",
      "support": 120.0,
      "resistance": 151.8,
      "indicators": {
        "rsi": 52.7,
        "macd_hist": -1.0166,
        "bb_position": 45.2,
        "vs_sma50": 1.1,
        "volume_ratio": 0.18,
        "stoch_k": 29.6
      },
      "individual_scores": {
        "rsi": 0.0,
        "macd": -1.0,
        "bollinger": 0.0,
        "ma": 0.6,
        "volume": -0.1,
        "stochastic": 0.2
      },
      "timestamp": "2026-02-06T15:11:06.784673"
    },
    {
      "ticker": "GOOG",
      "sector": "NASDAQ_Tech",
      "signal": "HOLD",
      "confidence": 20,
      "composite_score": 0.007,
      "current_price": 322.73,
      "daily_change": -2.59,
      "buy_range": "$306.75 - $317.41",
      "sell_range": "$328.06 - $344.05",
      "support": 306.92,
      "resistance": 350.15,
      "indicators": {
        "rsi": 43.5,
        "macd_hist": -1.6882,
        "bb_position": 3.5,
        "vs_sma50": 0.11,
        "volume_ratio": 0.37,
        "stoch_k": 36.6
      },
      "individual_scores": {
        "rsi": 0.0,
        "macd": -1.0,
        "bollinger": 0.8,
        "ma": 0.6,
        "volume": -0.1,
        "stochastic": 0.0
      },
      "timestamp": "2026-02-06T15:11:07.126618"
    },
    {
      "ticker": "GOOGL",
      "sector": "NASDAQ_Tech",
      "signal": "HOLD",
      "confidence": 20,
      "composite_score": 0.007,
      "current_price": 322.54,
      "daily_change": -2.63,
      "buy_range": "$306.47 - $317.18",
      "sell_range": "$327.9 - $343.96",
      "support": 306.46,
      "resistance": 349.0,
      "indicators": {
        "rsi": 43.4,
        "macd_hist": -1.6817,
        "bb_position": 3.0,
        "vs_sma50": 0.26,
        "volume_ratio": 0.35,
        "stoch_k": 37.8
      },
      "individual_scores": {
        "rsi": 0.0,
        "macd": -1.0,
        "bollinger": 0.8,
        "ma": 0.6,
        "volume": -0.1,
        "stochastic": 0.0
      },
      "timestamp": "2026-02-06T15:11:07.479919"
    },
    {
      "ticker": "IONQ",
      "sector": "NASDAQ_Tech",
      "signal": "HOLD",
      "confidence": 27,
      "composite_score": -0.077,
      "current_price": 33.04,
      "daily_change": 8.59,
      "buy_range": "$26.81 - $30.97",
      "sell_range": "$35.12 - $41.36",
      "support": 29.99,
      "resistance": 54.24,
      "indicators": {
        "rsi": 20.3,
        "macd_hist": -1.5315,
        "bb_position": 5.4,
        "vs_sma50": -30.11,
        "volume_ratio": 0.39,
        "stoch_k": 12.6
      },
      "individual_scores": {
        "rsi": 0.65,
        "macd": -0.5,
        "bollinger": 0.8,
        "ma": -1.0,
        "volume": -0.1,
        "stochastic": 0.5
      },
      "timestamp": "2026-02-06T15:11:07.826347"
    },
    {
      "ticker": "META",
      "sector": "NASDAQ_Tech",
      "signal": "SELL",
      "confidence": 48,
      "composite_score": -0.287,
      "current_price": 649.28,
      "daily_change": -3.12,
      "buy_range": "$609.28 - $635.94",
      "sell_range": "$662.61 - $702.6",
      "support": 600.0,
      "resistance": 744.0,
      "indicators": {
        "rsi": 55.8,
        "macd_hist": -0.3015,
        "bb_position": 43.9,
        "vs_sma50": -0.99,
        "volume_ratio": 0.21,
        "stoch_k": 34.2
      },
      "individual_scores": {
        "rsi": 0.0,
        "macd": -1.0,
        "bollinger": 0.0,
        "ma": -0.6,
        "volume": -0.1,
        "stochastic": 0.0
      },
      "timestamp": "2026-02-06T15:11:08.167500"
    },
    {
      "ticker": "MU",
      "sector": "NASDAQ_Tech",
      "signal": "HOLD",
      "confidence": 27,
      "composite_score": -0.077,
      "current_price": 384.39,
      "daily_change": 0.39,
      "buy_range": "$340.83 - $369.87",
      "sell_range": "$398.91 - $442.46",
      "support": 326.19,
      "resistance": 455.5,
      "indicators": {
        "rsi": 55.4,
        "macd_hist": -6.2846,
        "bb_position": 49.5,
        "vs_sma50": 22.6,
        "volume_ratio": 0.37,
        "stoch_k": 24.5
      },
      "individual_scores": {
        "rsi": 0.0,
        "macd": -1.0,
        "bollinger": 0.0,
        "ma": 0.6,
        "volume": -0.1,
        "stochastic": 0.0
      },
      "timestamp": "2026-02-06T15:11:09.042505"
    },
    {
      "ticker": "NET",
      "sector": "NASDAQ_Tech",
      "signal": "SELL",
      "confidence": 45,
      "composite_score": -0.256,
      "current_price": 162.2,
      "daily_change": -0.52,
      "buy_range": "$142.75 - $155.72",
      "sell_range": "$168.68 - $188.14",
      "support": 160.35,
      "resistance": 218.22,
      "indicators": {
        "rsi": 39.4,
        "macd_hist": -1.6716,
        "bb_position": 8.6,
        "vs_sma50": -15.49,
        "volume_ratio": 0.13,
        "stoch_k": 3.2
      },
      "individual_scores": {
        "rsi": 0.0,
        "macd": -1.0,
        "bollinger": 0.8,
        "ma": -1.0,
        "volume": -0.1,
        "stochastic": 0.5
      },
      "timestamp": "2026-02-06T15:11:09.326069"
    },
    {
      "ticker": "NVDA",
      "sector": "NASDAQ_Tech",
      "signal": "HOLD",
      "confidence": 35,
      "composite_score": -0.158,
      "current_price": 180.16,
      "daily_change": 4.82,
      "buy_range": "$170.78 - $177.03",
      "sell_range": "$183.29 - $192.67",
      "support": 171.03,
      "resistance": 194.49,
      "indicators": {
        "rsi": 44.4,
        "macd_hist": -1.3705,
        "bb_position": 30.2,
        "vs_sma50": -1.8,
        "volume_ratio": 0.32,
        "stoch_k": 38.9
      },
      "individual_scores": {
        "rsi": 0.0,
        "macd": -0.5,
        "bollinger": 0.0,
        "ma": -0.4,
        "volume": -0.1,
        "stochastic": 0.2
      },
      "timestamp": "2026-02-06T15:11:09.756798"
    },
    {
      "ticker": "PLTR",
      "sector": "NASDAQ_Tech",
      "signal": "HOLD",
      "confidence": 32,
      "composite_score": -0.128,
      "current_price": 133.98,
      "daily_change": 3.05,
      "buy_range": "$121.23 - $129.73",
      "sell_range": "$138.23 - $150.97",
      "support": 128.32,
      "resistance": 182.5,
      "indicators": {
        "rsi": 25.7,
        "macd_hist": -3.1635,
        "bb_position": 5.1,
        "vs_sma50": -22.51,
        "volume_ratio": 0.37,
        "stoch_k": 13.0
      },
      "individual_scores": {
        "rsi": 0.288,
        "macd": -0.5,
        "bollinger": 0.8,
        "ma": -1.0,
        "volume": -0.1,
        "stochastic": 0.5
      },
      "timestamp": "2026-02-06T15:11:10.061010"
    },
    {
      "ticker": "RGTI",
      "sector": "NASDAQ_Tech",
      "signal": "HOLD",
      "confidence": 35,
      "composite_score": -0.153,
      "current_price": 16.47,
      "daily_change": 9.95,
      "buy_range": "$13.46 - $15.46",
      "sell_range": "$17.47 - $20.47",
      "support": 14.83,
      "resistance": 26.7,
      "indicators": {
        "rsi": 22.8,
        "macd_hist": -0.6702,
        "bb_position": 12.1,
        "vs_sma50": -30.66,
        "volume_ratio": 0.33,
        "stoch_k": 14.0
      },
      "individual_scores": {
        "rsi": 0.482,
        "macd": -0.5,
        "bollinger": 0.3,
        "ma": -1.0,
        "volume": -0.1,
        "stochastic": 0.5
      },
      "timestamp": "2026-02-06T15:11:10.395765"
    },
    {
      "ticker": "SMCI",
      "sector": "NASDAQ_Tech",
      "signal": "HOLD",
      "confidence": 35,
      "composite_score": 0.154,
      "current_price": 33.29,
      "daily_change": 7.91,
      "buy_range": "$29.99 - $32.19",
      "sell_range": "$34.39 - $37.69",
      "support": 27.75,
      "resistance": 34.94,
      "indicators": {
        "rsi": 52.0,
        "macd_hist": 0.3317,
        "bb_position": 90.1,
        "vs_sma50": 5.8,
        "volume_ratio": 0.3,
        "stoch_k": 73.8
      },
      "individual_scores": {
        "rsi": 0.0,
        "macd": 1.0,
        "bollinger": -0.8,
        "ma": 0.4,
        "volume": -0.1,
        "stochastic": 0.0
      },
      "timestamp": "2026-02-06T15:11:10.672452"
    },
    {
      "ticker": "SNOW",
      "sector": "NASDAQ_Tech",
      "signal": "HOLD",
      "confidence": 28,
      "composite_score": -0.082,
      "current_price": 162.52,
      "daily_change": 3.71,
      "buy_range": "$147.44 - $157.5",
      "sell_range": "$167.55 - $182.64",
      "support": 156.08,
      "resistance": 226.83,
      "indicators": {
        "rsi": 20.8,
        "macd_hist": -4.7738,
        "bb_position": 2.8,
        "vs_sma50": -25.25,
        "volume_ratio": 0.41,
        "stoch_k": 9.6
      },
      "individual_scores": {
        "rsi": 0.613,
        "macd": -0.5,
        "bollinger": 0.8,
        "ma": -1.0,
        "volume": -0.1,
        "stochastic": 0.5
      },
      "timestamp": "2026-02-06T15:11:10.983731"
    },
    {
      "ticker": "STX",
      "sector": "NASDAQ_Tech",
      "signal": "BUY",
      "confidence": 42,
      "composite_score": 0.224,
      "current_price": 414.21,
      "daily_change": 2.16,
      "buy_range": "$365.64 - $398.02",
      "sell_range": "$430.4 - $478.96",
      "support": 280.67,
      "resistance": 459.41,
      "indicators": {
        "rsi": 67.9,
        "macd_hist": 2.4165,
        "bb_position": 71.6,
        "vs_sma50": 30.08,
        "volume_ratio": 0.17,
        "stoch_k": 67.1
      },
      "individual_scores": {
        "rsi": 0.0,
        "macd": 0.5,
        "bollinger": -0.3,
        "ma": 1.0,
        "volume": -0.1,
        "stochastic": 0.0
      },
      "timestamp": "2026-02-06T15:11:11.387390"
    },
    {
      "ticker": "SYM",
      "sector": "NASDAQ_Tech",
      "signal": "HOLD",
      "confidence": 35,
      "composite_score": -0.158,
      "current_price": 57.34,
      "daily_change": 6.62,
      "buy_range": "$50.74 - $55.14",
      "sell_range": "$59.54 - $66.14",
      "support": 50.87,
      "resistance": 73.97,
      "indicators": {
        "rsi": 31.8,
        "macd_hist": -0.6207,
        "bb_position": 34.4,
        "vs_sma50": -9.88,
        "volume_ratio": 0.56,
        "stoch_k": 37.7
      },
      "individual_scores": {
        "rsi": 0.0,
        "macd": -0.5,
        "bollinger": 0.0,
        "ma": -0.4,
        "volume": -0.1,
        "stochastic": 0.2
      },
      "timestamp": "2026-02-06T15:11:11.739790"
    },
    {
      "ticker": "TSLA",
      "sector": "NASDAQ_Tech",
      "signal": "HOLD",
      "confidence": 32,
      "composite_score": -0.126,
      "current_price": 408.31,
      "daily_change": 2.79,
      "buy_range": "$383.69 - $400.11",
      "sell_range": "$416.52 - $441.14",
      "support": 387.53,
      "resistance": 454.3,
      "indicators": {
        "rsi": 39.6,
        "macd_hist": -2.9738,
        "bb_position": 14.0,
        "vs_sma50": -8.14,
        "volume_ratio": 0.24,
        "stoch_k": 32.0
      },
      "individual_scores": {
        "rsi": 0.0,
        "macd": -0.5,
        "bollinger": 0.3,
        "ma": -0.4,
        "volume": -0.1,
        "stochastic": 0.2
      },
      "timestamp": "2026-02-06T15:11:12.084230"
    },
    {
      "ticker": "WDC",
      "sector": "NASDAQ_Tech",
      "signal": "BUY",
      "confidence": 42,
      "composite_score": 0.224,
      "current_price": 267.57,
      "daily_change": 2.84,
      "buy_range": "$232.92 - $256.02",
      "sell_range": "$279.12 - $313.78",
      "support": 186.0,
      "resistance": 296.5,
      "indicators": {
        "rsi": 62.9,
        "macd_hist": 0.0384,
        "bb_position": 72.1,
        "vs_sma50": 31.75,
        "volume_ratio": 0.24,
        "stoch_k": 62.2
      },
      "individual_scores": {
        "rsi": 0.0,
        "macd": 0.5,
        "bollinger": -0.3,
        "ma": 1.0,
        "volume": -0.1,
        "stochastic": 0.0
      },
      "timestamp": "2026-02-06T15:11:12.456381"
    },
    {
      "ticker": "COIN",
      "sector": "SP500_Broad",
      "signal": "HOLD",
      "confidence": 22,
      "composite_score": -0.028,
      "current_price": 157.23,
      "daily_change": 7.6,
      "buy_range": "$140.37 - $151.61",
      "sell_range": "$162.85 - $179.71",
      "support": 145.16,
      "resistance": 263.07,
      "indicators": {
        "rsi": 10.5,
        "macd_hist": -6.0588,
        "bb_position": 6.8,
        "vs_sma50": -33.7,
        "volume_ratio": 0.57,
        "stoch_k": 13.4
      },
      "individual_scores": {
        "rsi": 1.0,
        "macd": -0.5,
        "bollinger": 0.8,
        "ma": -1.0,
        "volume": -0.1,
        "stochastic": 0.5
      },
      "timestamp": "2026-02-06T15:11:12.769674"
    },
    {
      "ticker": "HOOD",
      "sector": "SP500_Broad",
      "signal": "HOLD",
      "confidence": 34,
      "composite_score": -0.146,
      "current_price": 81.31,
      "daily_change": 11.87,
      "buy_range": "$72.44 - $78.35",
      "sell_range": "$84.27 - $93.14",
      "support": 71.87,
      "resistance": 120.88,
      "indicators": {
        "rsi": 20.9,
        "macd_hist": -2.7288,
        "bb_position": 10.9,
        "vs_sma50": -29.03,
        "volume_ratio": 0.72,
        "stoch_k": 23.8
      },
      "individual_scores": {
        "rsi": 0.607,
        "macd": -0.5,
        "bollinger": 0.3,
        "ma": -1.0,
        "volume": -0.1,
        "stochastic": 0.2
      },
      "timestamp": "2026-02-06T15:11:13.053768"
    },
    {
      "ticker": "ISRG",
      "sector": "SP500_Broad",
      "signal": "HOLD",
      "confidence": 35,
      "composite_score": -0.155,
      "current_price": 487.76,
      "daily_change": 2.4,
      "buy_range": "$467.48 - $481.0",
      "sell_range": "$494.52 - $514.8",
      "support": 465.69,
      "resistance": 589.58,
      "indicators": {
        "rsi": 21.9,
        "macd_hist": -4.467,
        "bb_position": 21.5,
        "vs_sma50": -11.4,
        "volume_ratio": 0.21,
        "stoch_k": 29.7
      },
      "individual_scores": {
        "rsi": 0.541,
        "macd": -0.5,
        "bollinger": 0.3,
        "ma": -1.0,
        "volume": -0.1,
        "stochastic": 0.2
      },
      "timestamp": "2026-02-06T15:11:13.369920"
    },
    {
      "ticker": "SOFI",
      "sector": "SP500_Broad",
      "signal": "HOLD",
      "confidence": 34,
      "composite_score": -0.141,
      "current_price": 20.72,
      "daily_change": 6.49,
      "buy_range": "$18.74 - $20.06",
      "sell_range": "$21.38 - $23.37",
      "support": 19.19,
      "resistance": 28.38,
      "indicators": {
        "rsi": 20.4,
        "macd_hist": -0.5377,
        "bb_position": 10.1,
        "vs_sma50": -21.32,
        "volume_ratio": 0.34,
        "stoch_k": 21.2
      },
      "individual_scores": {
        "rsi": 0.64,
        "macd": -0.5,
        "bollinger": 0.3,
        "ma": -1.0,
        "volume": -0.1,
        "stochastic": 0.2
      },
      "timestamp": "2026-02-06T15:11:13.648965"
    },
    {
      "ticker": "BEAM",
      "sector": "Biotech",
      "signal": "HOLD",
      "confidence": 31,
      "composite_score": -0.115,
      "current_price": 25.58,
      "daily_change": 3.44,
      "buy_range": "$22.26 - $24.47",
      "sell_range": "$26.69 - $30.0",
      "support": 24.3,
      "resistance": 36.44,
      "indicators": {
        "rsi": 31.3,
        "macd_hist": -0.8251,
        "bb_position": 12.0,
        "vs_sma50": -9.32,
        "volume_ratio": 0.1,
        "stoch_k": 11.6
      },
      "individual_scores": {
        "rsi": 0.0,
        "macd": -0.5,
        "bollinger": 0.3,
        "ma": -0.4,
        "volume": -0.1,
        "stochastic": 0.5
      },
      "timestamp": "2026-02-06T15:11:13.983637"
    },
    {
      "ticker": "CRSP",
      "sector": "Biotech",
      "signal": "SELL",
      "confidence": 45,
      "composite_score": -0.256,
      "current_price": 46.78,
      "daily_change": 1.97,
      "buy_range": "$41.91 - $45.16",
      "sell_range": "$48.41 - $53.29",
      "support": 45.53,
      "resistance": 60.86,
      "indicators": {
        "rsi": 38.4,
        "macd_hist": -0.8456,
        "bb_position": 2.0,
        "vs_sma50": -14.39,
        "volume_ratio": 0.16,
        "stoch_k": 8.2
      },
      "individual_scores": {
        "rsi": 0.0,
        "macd": -1.0,
        "bollinger": 0.8,
        "ma": -1.0,
        "volume": -0.1,
        "stochastic": 0.5
      },
      "timestamp": "2026-02-06T15:11:14.335951"
    },
    {
      "ticker": "DNA",
      "sector": "Biotech",
      "signal": "SELL",
      "confidence": 46,
      "composite_score": -0.262,
      "current_price": 9.04,
      "daily_change": 8.62,
      "buy_range": "$7.88 - $8.65",
      "sell_range": "$9.42 - $10.58",
      "support": 7.73,
      "resistance": 11.1,
      "indicators": {
        "rsi": 45.6,
        "macd_hist": -0.129,
        "bb_position": 34.6,
        "vs_sma50": -0.47,
        "volume_ratio": 0.54,
        "stoch_k": 38.8
      },
      "individual_scores": {
        "rsi": 0.0,
        "macd": -0.5,
        "bollinger": 0.0,
        "ma": -1.0,
        "volume": -0.1,
        "stochastic": 0.2
      },
      "timestamp": "2026-02-06T15:11:14.640469"
    },
    {
      "ticker": "RXRX",
      "sector": "Biotech",
      "signal": "HOLD",
      "confidence": 36,
      "composite_score": -0.168,
      "current_price": 3.77,
      "daily_change": 5.76,
      "buy_range": "$3.33 - $3.62",
      "sell_range": "$3.91 - $4.34",
      "support": 3.54,
      "resistance": 5.24,
      "indicators": {
        "rsi": 31.6,
        "macd_hist": -0.104,
        "bb_position": 5.8,
        "vs_sma50": -15.41,
        "volume_ratio": 0.24,
        "stoch_k": 13.2
      },
      "individual_scores": {
        "rsi": 0.0,
        "macd": -0.5,
        "bollinger": 0.8,
        "ma": -1.0,
        "volume": -0.1,
        "stochastic": 0.5
      },
      "timestamp": "2026-02-06T15:11:14.916042"
    },
    {
      "ticker": "ASTS",
      "sector": "Space",
      "signal": "HOLD",
      "confidence": 22,
      "composite_score": -0.028,
      "current_price": 98.07,
      "daily_change": 5.15,
      "buy_range": "$79.21 - $91.78",
      "sell_range": "$104.36 - $123.22",
      "support": 88.75,
      "resistance": 129.89,
      "indicators": {
        "rsi": 42.0,
        "macd_hist": -2.9279,
        "bb_position": 26.8,
        "vs_sma50": 13.15,
        "volume_ratio": 0.24,
        "stoch_k": 17.4
      },
      "individual_scores": {
        "rsi": 0.0,
        "macd": -1.0,
        "bollinger": 0.3,
        "ma": 0.6,
        "volume": -0.1,
        "stochastic": 0.5
      },
      "timestamp": "2026-02-06T15:11:15.230273"
    },
    {
      "ticker": "IRDM",
      "sector": "Space",
      "signal": "HOLD",
      "confidence": 38,
      "composite_score": -0.182,
      "current_price": 19.32,
      "daily_change": 0.99,
      "buy_range": "$17.61 - $18.75",
      "sell_range": "$19.89 - $21.6",
      "support": 18.07,
      "resistance": 22.18,
      "indicators": {
        "rsi": 52.1,
        "macd_hist": -0.2476,
        "bb_position": 31.1,
        "vs_sma50": 4.67,
        "volume_ratio": 0.11,
        "stoch_k": 20.8
      },
      "individual_scores": {
        "rsi": 0.0,
        "macd": -1.0,
        "bollinger": 0.0,
        "ma": 0.0,
        "volume": -0.1,
        "stochastic": 0.0
      },
      "timestamp": "2026-02-06T15:11:15.607991"
    },
    {
      "ticker": "RKLB",
      "sector": "Space",
      "signal": "HOLD",
      "confidence": 33,
      "composite_score": -0.137,
      "current_price": 68.53,
      "daily_change": 3.33,
      "buy_range": "$56.8 - $64.62",
      "sell_range": "$72.44 - $84.17",
      "support": 65.2,
      "resistance": 99.58,
      "indicators": {
        "rsi": 28.6,
        "macd_hist": -3.2457,
        "bb_position": 1.7,
        "vs_sma50": -3.0,
        "volume_ratio": 0.23,
        "stoch_k": 10.1
      },
      "individual_scores": {
        "rsi": 0.096,
        "macd": -1.0,
        "bollinger": 0.8,
        "ma": -0.4,
        "volume": -0.1,
        "stochastic": 0.5
      },
      "timestamp": "2026-02-06T15:11:15.932189"
    },
    {
      "ticker": "ENPH",
      "sector": "CleanEnergy",
      "signal": "BUY",
      "confidence": 43,
      "composite_score": 0.234,
      "current_price": 49.11,
      "daily_change": 3.89,
      "buy_range": "$43.55 - $47.26",
      "sell_range": "$50.96 - $56.53",
      "support": 33.65,
      "resistance": 52.93,
      "indicators": {
        "rsi": 70.8,
        "macd_hist": 1.0608,
        "bb_position": 101.8,
        "vs_sma50": 41.21,
        "volume_ratio": 0.24,
        "stoch_k": 80.2
      },
      "individual_scores": {
        "rsi": -0.053,
        "macd": 1.0,
        "bollinger": -0.8,
        "ma": 1.0,
        "volume": -0.1,
        "stochastic": -0.5
      },
      "timestamp": "2026-02-06T15:11:16.247106"
    },
    {
      "ticker": "FSLR",
      "sector": "CleanEnergy",
      "signal": "HOLD",
      "confidence": 36,
      "composite_score": -0.168,
      "current_price": 223.63,
      "daily_change": -4.58,
      "buy_range": "$203.67 - $216.98",
      "sell_range": "$230.29 - $250.25",
      "support": 214.0,
      "resistance": 252.52,
      "indicators": {
        "rsi": 38.7,
        "macd_hist": -0.4219,
        "bb_position": 0.3,
        "vs_sma50": -11.56,
        "volume_ratio": 0.34,
        "stoch_k": 25.8
      },
      "individual_scores": {
        "rsi": 0.0,
        "macd": -1.0,
        "bollinger": 0.8,
        "ma": -0.4,
        "volume": -0.1,
        "stochastic": 0.0
      },
      "timestamp": "2026-02-06T15:11:16.577276"
    },
    {
      "ticker": "QS",
      "sector": "CleanEnergy",
      "signal": "HOLD",
      "confidence": 36,
      "composite_score": -0.163,
      "current_price": 8.2,
      "daily_change": 5.67,
      "buy_range": "$7.17 - $7.86",
      "sell_range": "$8.54 - $9.57",
      "support": 7.72,
      "resistance": 11.93,
      "indicators": {
        "rsi": 29.4,
        "macd_hist": -0.1761,
        "bb_position": 8.7,
        "vs_sma50": -24.63,
        "volume_ratio": 0.23,
        "stoch_k": 11.4
      },
      "individual_scores": {
        "rsi": 0.039,
        "macd": -0.5,
        "bollinger": 0.8,
        "ma": -1.0,
        "volume": -0.1,
        "stochastic": 0.5
      },
      "timestamp": "2026-02-06T15:11:16.887534"
    },
    {
      "ticker": "LEU",
      "sector": "Nuclear",
      "signal": "HOLD",
      "confidence": 32,
      "composite_score": -0.126,
      "current_price": 254.54,
      "daily_change": 5.14,
      "buy_range": "$206.16 - $238.42",
      "sell_range": "$270.67 - $319.06",
      "support": 230.51,
      "resistance": 345.6,
      "indicators": {
        "rsi": 34.1,
        "macd_hist": -7.8806,
        "bb_position": 11.2,
        "vs_sma50": -7.35,
        "volume_ratio": 0.17,
        "stoch_k": 20.9
      },
      "individual_scores": {
        "rsi": 0.0,
        "macd": -0.5,
        "bollinger": 0.3,
        "ma": -0.4,
        "volume": -0.1,
        "stochastic": 0.2
      },
      "timestamp": "2026-02-06T15:11:17.157690"
    }
  ],
  "summary": {
    "strong_buy": [],
    "buy": [
      "STX",
      "WDC",
      "ENPH"
    ],
    "hold": [
      "AMZN",
      "ANET",
      "GOOG",
      "GOOGL",
      "IONQ",
      "MU",
      "NVDA",
      "PLTR",
      "RGTI",
      "SMCI",
      "SNOW",
      "SYM",
      "TSLA",
      "COIN",
      "HOOD",
      "ISRG",
      "SOFI",
      "BEAM",
      "RXRX",
      "ASTS",
      "IRDM",
      "RKLB",
      "FSLR",
      "QS",
      "LEU"
    ],
    "sell": [
      "AMD",
      "META",
      "NET",
      "CRSP",
      "DNA"
    ],
    "strong_sell": []
  },
  "generated_at": "2026-02-06T15:11:05.745582",
  "options": [
    {
      "ticker": "AMD",
      "current_price": 204.52,
      "signal": "SELL",
      "target_price": 235.95,
      "recommendation": "$200.0 CALL exp 2027-01-15 \u2192 Target $235.95",
      "options": [
        {
          "strike": 200.0,
          "bid": 47.25,
          "ask": 48.9,
          "mid_price": 48.08,
          "last_price": 48.15,
          "volume": 95,
          "open_interest": 10759,
          "implied_volatility": 59.1,
          "delta": 0.55,
          "intrinsic": 4.52,
          "extrinsic": 43.55,
          "moneyness": 2.2,
          "moneyness_label": "ITM",
          "break_even": 248.07,
          "target_price": 235.95,
          "return_at_target": -25.2,
          "max_loss": -100,
          "leverage": 2.3,
          "daily_theta_pct": 0.265,
          "liquidity_score": 100,
          "risk_reward": 0,
          "expiry": "2027-01-15",
          "days_to_expiry": 342,
          "option_type": "CALL",
          "score": 36
        }
      ]
    },
    {
      "ticker": "AMZN",
      "current_price": 202.32,
      "signal": "HOLD",
      "target_price": 218.74,
      "recommendation": "$220.0 CALL exp 2026-11-20 \u2192 Target $218.74",
      "options": [
        {
          "strike": 220.0,
          "bid": 21.95,
          "ask": 22.25,
          "mid_price": 22.1,
          "last_price": 21.0,
          "volume": 9,
          "open_interest": 631,
          "implied_volatility": 40.4,
          "delta": 0.45,
          "intrinsic": 0,
          "extrinsic": 22.1,
          "moneyness": -8.7,
          "moneyness_label": "OTM",
          "break_even": 242.1,
          "target_price": 218.74,
          "return_at_target": -100.0,
          "max_loss": -100,
          "leverage": 4.1,
          "daily_theta_pct": 0.35,
          "liquidity_score": 7.2,
          "risk_reward": 0,
          "expiry": "2026-11-20",
          "days_to_expiry": 286,
          "option_type": "CALL",
          "score": 44
        }
      ]
    },
    {
      "ticker": "ANET",
      "current_price": 132.95,
      "signal": "HOLD",
      "target_price": 147.31,
      "recommendation": "$130.0 CALL exp 2027-01-15 \u2192 Target $147.31",
      "options": [
        {
          "strike": 130.0,
          "bid": 28.4,
          "ask": 31.4,
          "mid_price": 29.9,
          "last_price": 27.15,
          "volume": 191,
          "open_interest": 1333,
          "implied_volatility": 56.4,
          "delta": 0.55,
          "intrinsic": 2.95,
          "extrinsic": 26.95,
          "moneyness": 2.2,
          "moneyness_label": "ITM",
          "break_even": 159.9,
          "target_price": 147.31,
          "return_at_target": -42.1,
          "max_loss": -100,
          "leverage": 2.4,
          "daily_theta_pct": 0.264,
          "liquidity_score": 32.4,
          "risk_reward": 0,
          "expiry": "2027-01-15",
          "days_to_expiry": 342,
          "option_type": "CALL",
          "score": 34
        }
      ]
    },
    {
      "ticker": "GOOG",
      "current_price": 322.73,
      "signal": "HOLD",
      "target_price": 344.05,
      "recommendation": "$355.0 CALL exp 2026-12-18 \u2192 Target $344.05",
      "options": [
        {
          "strike": 355.0,
          "bid": 36.15,
          "ask": 36.5,
          "mid_price": 36.33,
          "last_price": 37.76,
          "volume": 51,
          "open_interest": 445,
          "implied_volatility": 40.6,
          "delta": 0.45,
          "intrinsic": 0,
          "extrinsic": 36.33,
          "moneyness": -10.0,
          "moneyness_label": "OTM",
          "break_even": 391.32,
          "target_price": 344.05,
          "return_at_target": -100.0,
          "max_loss": -100,
          "leverage": 4.0,
          "daily_theta_pct": 0.318,
          "liquidity_score": 9.6,
          "risk_reward": 0,
          "expiry": "2026-12-18",
          "days_to_expiry": 314,
          "option_type": "CALL",
          "score": 44
        }
      ]
    },
    {
      "ticker": "GOOGL",
      "current_price": 322.54,
      "signal": "HOLD",
      "target_price": 343.96,
      "recommendation": "$55.0 CALL exp 2027-06-17 \u2192 Target $343.96",
      "options": [
        {
          "strike": 55.0,
          "bid": 0,
          "ask": 0,
          "mid_price": 97.23,
          "last_price": 97.23,
          "volume": 0,
          "open_interest": 0,
          "implied_volatility": 0.0,
          "delta": 0.8,
          "intrinsic": 267.54,
          "extrinsic": -170.31,
          "moneyness": 82.9,
          "moneyness_label": "ITM",
          "break_even": 152.23,
          "target_price": 343.96,
          "return_at_target": 197.2,
          "max_loss": -100,
          "leverage": 2.7,
          "daily_theta_pct": -0.354,
          "liquidity_score": 0.0,
          "risk_reward": 1.97,
          "expiry": "2027-06-17",
          "days_to_expiry": 495,
          "option_type": "CALL",
          "score": 69.3
        }
      ]
    },
    {
      "ticker": "IONQ",
      "current_price": 33.04,
      "signal": "HOLD",
      "target_price": 41.36,
      "recommendation": "$35.0 CALL exp 2027-01-15 \u2192 Target $41.36",
      "options": [
        {
          "strike": 35.0,
          "bid": 9.85,
          "ask": 11.95,
          "mid_price": 10.9,
          "last_price": 10.5,
          "volume": 6,
          "open_interest": 2819,
          "implied_volatility": 92.7,
          "delta": 0.45,
          "intrinsic": 0,
          "extrinsic": 10.9,
          "moneyness": -5.9,
          "moneyness_label": "OTM",
          "break_even": 45.9,
          "target_price": 41.36,
          "return_at_target": -41.7,
          "max_loss": -100,
          "leverage": 1.4,
          "daily_theta_pct": 0.292,
          "liquidity_score": 28.8,
          "risk_reward": 0,
          "expiry": "2027-01-15",
          "days_to_expiry": 342,
          "option_type": "CALL",
          "score": 33
        }
      ]
    },
    {
      "ticker": "META",
      "current_price": 649.28,
      "signal": "SELL",
      "target_price": 702.6,
      "recommendation": "$710.0 CALL exp 2026-11-20 \u2192 Target $702.60",
      "options": [
        {
          "strike": 710.0,
          "bid": 72.45,
          "ask": 73.25,
          "mid_price": 72.85,
          "last_price": 83.6,
          "volume": 2,
          "open_interest": 17,
          "implied_volatility": 41.9,
          "delta": 0.45,
          "intrinsic": 0,
          "extrinsic": 72.85,
          "moneyness": -9.4,
          "moneyness_label": "OTM",
          "break_even": 782.85,
          "target_price": 702.6,
          "return_at_target": -100.0,
          "max_loss": -100,
          "leverage": 4.0,
          "daily_theta_pct": 0.35,
          "liquidity_score": 0.4,
          "risk_reward": 0,
          "expiry": "2026-11-20",
          "days_to_expiry": 286,
          "option_type": "CALL",
          "score": 43
        }
      ]
    },
    {
      "ticker": "MU",
      "current_price": 384.39,
      "signal": "HOLD",
      "target_price": 442.46,
      "recommendation": "$40.0 CALL exp 2026-12-18 \u2192 Target $442.46",
      "options": [
        {
          "strike": 40.0,
          "bid": 80.15,
          "ask": 81.45,
          "mid_price": 80.8,
          "last_price": 57.82,
          "volume": 1,
          "open_interest": 22,
          "implied_volatility": 0.0,
          "delta": 0.8,
          "intrinsic": 344.39,
          "extrinsic": -263.59,
          "moneyness": 89.6,
          "moneyness_label": "ITM",
          "break_even": 120.8,
          "target_price": 442.46,
          "return_at_target": 398.1,
          "max_loss": -100,
          "leverage": 3.8,
          "daily_theta_pct": -1.039,
          "liquidity_score": 0.3,
          "risk_reward": 3.98,
          "expiry": "2026-12-18",
          "days_to_expiry": 314,
          "option_type": "CALL",
          "score": 75
        }
      ]
    },
    {
      "ticker": "NET",
      "current_price": 162.2,
      "signal": "SELL",
      "target_price": 188.14,
      "recommendation": "$82.5 CALL exp 2027-01-15 \u2192 Target $188.14",
      "options": [
        {
          "strike": 82.5,
          "bid": 0,
          "ask": 0,
          "mid_price": 59.17,
          "last_price": 59.17,
          "volume": 1,
          "open_interest": 2,
          "implied_volatility": 0.0,
          "delta": 0.8,
          "intrinsic": 79.7,
          "extrinsic": -20.53,
          "moneyness": 49.1,
          "moneyness_label": "ITM",
          "break_even": 141.67,
          "target_price": 188.14,
          "return_at_target": 78.5,
          "max_loss": -100,
          "leverage": 2.2,
          "daily_theta_pct": -0.101,
          "liquidity_score": 0.1,
          "risk_reward": 0.79,
          "expiry": "2027-01-15",
          "days_to_expiry": 342,
          "option_type": "CALL",
          "score": 39.6
        }
      ]
    },
    {
      "ticker": "NVDA",
      "current_price": 180.16,
      "signal": "HOLD",
      "target_price": 192.67,
      "recommendation": "$180.0 CALL exp 2026-08-21 \u2192 Target $192.67",
      "options": [
        {
          "strike": 180.0,
          "bid": 24.75,
          "ask": 25.0,
          "mid_price": 24.88,
          "last_price": 24.95,
          "volume": 139,
          "open_interest": 15935,
          "implied_volatility": 47.3,
          "delta": 0.55,
          "intrinsic": 0.16,
          "extrinsic": 24.72,
          "moneyness": 0.1,
          "moneyness_label": "ATM",
          "break_even": 204.88,
          "target_price": 192.67,
          "return_at_target": -49.1,
          "max_loss": -100,
          "leverage": 4.0,
          "daily_theta_pct": 0.51,
          "liquidity_score": 100,
          "risk_reward": 0,
          "expiry": "2026-08-21",
          "days_to_expiry": 195,
          "option_type": "CALL",
          "score": 43
        }
      ]
    },
    {
      "ticker": "PLTR",
      "current_price": 133.98,
      "signal": "HOLD",
      "target_price": 150.97,
      "recommendation": "$130.0 CALL exp 2027-01-15 \u2192 Target $150.97",
      "options": [
        {
          "strike": 130.0,
          "bid": 33.1,
          "ask": 33.45,
          "mid_price": 33.28,
          "last_price": 33.45,
          "volume": 249,
          "open_interest": 4418,
          "implied_volatility": 61.7,
          "delta": 0.55,
          "intrinsic": 3.98,
          "extrinsic": 29.3,
          "moneyness": 3.0,
          "moneyness_label": "ITM",
          "break_even": 163.28,
          "target_price": 150.97,
          "return_at_target": -37.0,
          "max_loss": -100,
          "leverage": 2.2,
          "daily_theta_pct": 0.257,
          "liquidity_score": 69.1,
          "risk_reward": 0,
          "expiry": "2027-01-15",
          "days_to_expiry": 342,
          "option_type": "CALL",
          "score": 36
        }
      ]
    },
    {
      "ticker": "RGTI",
      "current_price": 16.47,
      "signal": "HOLD",
      "target_price": 20.47,
      "recommendation": "$17.0 CALL exp 2027-01-15 \u2192 Target $20.47",
      "options": [
        {
          "strike": 17.0,
          "bid": 4.9,
          "ask": 5.7,
          "mid_price": 5.3,
          "last_price": 4.8,
          "volume": 196,
          "open_interest": 1400,
          "implied_volatility": 88.0,
          "delta": 0.45,
          "intrinsic": 0,
          "extrinsic": 5.3,
          "moneyness": -3.2,
          "moneyness_label": "OTM",
          "break_even": 22.3,
          "target_price": 20.47,
          "return_at_target": -34.5,
          "max_loss": -100,
          "leverage": 1.4,
          "daily_theta_pct": 0.292,
          "liquidity_score": 33.6,
          "risk_reward": 0,
          "expiry": "2027-01-15",
          "days_to_expiry": 342,
          "option_type": "CALL",
          "score": 33
        }
      ]
    },
    {
      "ticker": "SMCI",
      "current_price": 33.29,
      "signal": "HOLD",
      "target_price": 37.69,
      "recommendation": "$36.0 CALL exp 2026-12-18 \u2192 Target $37.69",
      "options": [
        {
          "strike": 36.0,
          "bid": 7.2,
          "ask": 7.75,
          "mid_price": 7.47,
          "last_price": 6.8,
          "volume": 67,
          "open_interest": 2394,
          "implied_volatility": 69.0,
          "delta": 0.45,
          "intrinsic": 0,
          "extrinsic": 7.47,
          "moneyness": -8.1,
          "moneyness_label": "OTM",
          "break_even": 43.48,
          "target_price": 37.69,
          "return_at_target": -77.4,
          "max_loss": -100,
          "leverage": 2.0,
          "daily_theta_pct": 0.318,
          "liquidity_score": 30.6,
          "risk_reward": 0,
          "expiry": "2026-12-18",
          "days_to_expiry": 314,
          "option_type": "CALL",
          "score": 34
        }
      ]
    },
    {
      "ticker": "SNOW",
      "current_price": 162.52,
      "signal": "HOLD",
      "target_price": 182.64,
      "recommendation": "$155.0 CALL exp 2027-01-15 \u2192 Target $182.64",
      "options": [
        {
          "strike": 155.0,
          "bid": 39.0,
          "ask": 45.35,
          "mid_price": 42.17,
          "last_price": 39.47,
          "volume": 3,
          "open_interest": 2292,
          "implied_volatility": 62.6,
          "delta": 0.55,
          "intrinsic": 7.52,
          "extrinsic": 34.65,
          "moneyness": 4.6,
          "moneyness_label": "ITM",
          "break_even": 197.18,
          "target_price": 182.64,
          "return_at_target": -34.5,
          "max_loss": -100,
          "leverage": 2.1,
          "daily_theta_pct": 0.24,
          "liquidity_score": 23.2,
          "risk_reward": 0,
          "expiry": "2027-01-15",
          "days_to_expiry": 342,
          "option_type": "CALL",
          "score": 34
        }
      ]
    },
    {
      "ticker": "STX",
      "current_price": 414.21,
      "signal": "BUY",
      "target_price": 478.96,
      "recommendation": "$45.0 CALL exp 2027-01-15 \u2192 Target $478.96",
      "options": [
        {
          "strike": 45.0,
          "bid": 94.5,
          "ask": 98.6,
          "mid_price": 96.55,
          "last_price": 72.4,
          "volume": 1,
          "open_interest": 0,
          "implied_volatility": 0.0,
          "delta": 0.8,
          "intrinsic": 369.21,
          "extrinsic": -272.66,
          "moneyness": 89.1,
          "moneyness_label": "ITM",
          "break_even": 141.55,
          "target_price": 478.96,
          "return_at_target": 349.5,
          "max_loss": -100,
          "leverage": 3.4,
          "daily_theta_pct": -0.826,
          "liquidity_score": 0.1,
          "risk_reward": 3.49,
          "expiry": "2027-01-15",
          "days_to_expiry": 342,
          "option_type": "CALL",
          "score": 75
        }
      ]
    },
    {
      "ticker": "SYM",
      "current_price": 57.34,
      "signal": "HOLD",
      "target_price": 66.14,
      "recommendation": "$55.0 CALL exp 2026-11-20 \u2192 Target $66.14",
      "options": [
        {
          "strike": 55.0,
          "bid": 17.0,
          "ask": 20.0,
          "mid_price": 18.5,
          "last_price": 14.6,
          "volume": 1,
          "open_interest": 2,
          "implied_volatility": 88.3,
          "delta": 0.55,
          "intrinsic": 2.34,
          "extrinsic": 16.16,
          "moneyness": 4.1,
          "moneyness_label": "ITM",
          "break_even": 73.5,
          "target_price": 66.14,
          "return_at_target": -39.8,
          "max_loss": -100,
          "leverage": 1.7,
          "daily_theta_pct": 0.305,
          "liquidity_score": 0.1,
          "risk_reward": 0,
          "expiry": "2026-11-20",
          "days_to_expiry": 286,
          "option_type": "CALL",
          "score": 30
        }
      ]
    },
    {
      "ticker": "TSLA",
      "current_price": 408.31,
      "signal": "HOLD",
      "target_price": 441.14,
      "recommendation": "$35.0 CALL exp 2026-12-18 \u2192 Target $441.14",
      "options": [
        {
          "strike": 35.0,
          "bid": 0,
          "ask": 0,
          "mid_price": 205.22,
          "last_price": 205.22,
          "volume": 142,
          "open_interest": 0,
          "implied_volatility": 0.0,
          "delta": 0.8,
          "intrinsic": 373.31,
          "extrinsic": -168.09,
          "moneyness": 91.4,
          "moneyness_label": "ITM",
          "break_even": 240.22,
          "target_price": 441.14,
          "return_at_target": 97.9,
          "max_loss": -100,
          "leverage": 1.6,
          "daily_theta_pct": -0.261,
          "liquidity_score": 14.2,
          "risk_reward": 0.98,
          "expiry": "2026-12-18",
          "days_to_expiry": 314,
          "option_type": "CALL",
          "score": 45.5
        }
      ]
    },
    {
      "ticker": "WDC",
      "current_price": 267.57,
      "signal": "BUY",
      "target_price": 313.78,
      "recommendation": "$22.5 CALL exp 2026-12-18 \u2192 Target $313.78",
      "options": [
        {
          "strike": 22.5,
          "bid": 28.05,
          "ask": 30.9,
          "mid_price": 29.48,
          "last_price": 21.1,
          "volume": 1,
          "open_interest": 39,
          "implied_volatility": 0.0,
          "delta": 0.8,
          "intrinsic": 245.07,
          "extrinsic": -215.6,
          "moneyness": 91.6,
          "moneyness_label": "ITM",
          "break_even": 51.98,
          "target_price": 313.78,
          "return_at_target": 888.2,
          "max_loss": -100,
          "leverage": 7.3,
          "daily_theta_pct": -2.329,
          "liquidity_score": 0.5,
          "risk_reward": 8.88,
          "expiry": "2026-12-18",
          "days_to_expiry": 314,
          "option_type": "CALL",
          "score": 80
        }
      ]
    },
    {
      "ticker": "COIN",
      "current_price": 157.23,
      "signal": "HOLD",
      "target_price": 179.71,
      "recommendation": "$170.0 CALL exp 2026-12-18 \u2192 Target $179.71",
      "options": [
        {
          "strike": 170.0,
          "bid": 34.9,
          "ask": 39.35,
          "mid_price": 37.12,
          "last_price": 32.57,
          "volume": 44,
          "open_interest": 73,
          "implied_volatility": 72.2,
          "delta": 0.45,
          "intrinsic": 0,
          "extrinsic": 37.12,
          "moneyness": -8.1,
          "moneyness_label": "OTM",
          "break_even": 207.12,
          "target_price": 179.71,
          "return_at_target": -73.8,
          "max_loss": -100,
          "leverage": 1.9,
          "daily_theta_pct": 0.318,
          "liquidity_score": 5.1,
          "risk_reward": 0,
          "expiry": "2026-12-18",
          "days_to_expiry": 314,
          "option_type": "CALL",
          "score": 31
        }
      ]
    },
    {
      "ticker": "HOOD",
      "current_price": 81.31,
      "signal": "HOLD",
      "target_price": 93.14,
      "recommendation": "$85.0 CALL exp 2027-01-15 \u2192 Target $93.14",
      "options": [
        {
          "strike": 85.0,
          "bid": 20.55,
          "ask": 22.3,
          "mid_price": 21.43,
          "last_price": 21.12,
          "volume": 31,
          "open_interest": 6167,
          "implied_volatility": 73.2,
          "delta": 0.45,
          "intrinsic": 0,
          "extrinsic": 21.43,
          "moneyness": -4.5,
          "moneyness_label": "OTM",
          "break_even": 106.42,
          "target_price": 93.14,
          "return_at_target": -62.0,
          "max_loss": -100,
          "leverage": 1.7,
          "daily_theta_pct": 0.292,
          "liquidity_score": 64.8,
          "risk_reward": 0,
          "expiry": "2027-01-15",
          "days_to_expiry": 342,
          "option_type": "CALL",
          "score": 35
        }
      ]
    },
    {
      "ticker": "ISRG",
      "current_price": 487.76,
      "signal": "HOLD",
      "target_price": 514.8,
      "recommendation": "$520.0 CALL exp 2026-12-18 \u2192 Target $514.80",
      "options": [
        {
          "strike": 520.0,
          "bid": 48.4,
          "ask": 55.7,
          "mid_price": 52.05,
          "last_price": 48.4,
          "volume": 32,
          "open_interest": 72,
          "implied_volatility": 37.6,
          "delta": 0.45,
          "intrinsic": 0,
          "extrinsic": 52.05,
          "moneyness": -6.6,
          "moneyness_label": "OTM",
          "break_even": 572.05,
          "target_price": 514.8,
          "return_at_target": -100.0,
          "max_loss": -100,
          "leverage": 4.2,
          "daily_theta_pct": 0.318,
          "liquidity_score": 3.9,
          "risk_reward": 0,
          "expiry": "2026-12-18",
          "days_to_expiry": 314,
          "option_type": "CALL",
          "score": 43
        }
      ]
    },
    {
      "ticker": "SOFI",
      "current_price": 20.72,
      "signal": "HOLD",
      "target_price": 23.37,
      "recommendation": "$20.0 CALL exp 2026-12-18 \u2192 Target $23.37",
      "options": [
        {
          "strike": 20.0,
          "bid": 5.15,
          "ask": 5.3,
          "mid_price": 5.22,
          "last_price": 5.22,
          "volume": 188,
          "open_interest": 5955,
          "implied_volatility": 65.1,
          "delta": 0.55,
          "intrinsic": 0.72,
          "extrinsic": 4.51,
          "moneyness": 3.5,
          "moneyness_label": "ITM",
          "break_even": 25.23,
          "target_price": 23.37,
          "return_at_target": -35.5,
          "max_loss": -100,
          "leverage": 2.2,
          "daily_theta_pct": 0.275,
          "liquidity_score": 78.3,
          "risk_reward": 0,
          "expiry": "2026-12-18",
          "days_to_expiry": 314,
          "option_type": "CALL",
          "score": 36
        }
      ]
    },
    {
      "ticker": "BEAM",
      "current_price": 25.58,
      "signal": "HOLD",
      "target_price": 30.0,
      "recommendation": "$25.0 CALL exp 2027-01-15 \u2192 Target $30.00",
      "options": [
        {
          "strike": 25.0,
          "bid": 6.0,
          "ask": 10.5,
          "mid_price": 8.25,
          "last_price": 8.21,
          "volume": 2,
          "open_interest": 69,
          "implied_volatility": 82.7,
          "delta": 0.55,
          "intrinsic": 0.58,
          "extrinsic": 7.67,
          "moneyness": 2.3,
          "moneyness_label": "ITM",
          "break_even": 33.25,
          "target_price": 30.0,
          "return_at_target": -39.4,
          "max_loss": -100,
          "leverage": 1.7,
          "daily_theta_pct": 0.272,
          "liquidity_score": 0.9,
          "risk_reward": 0,
          "expiry": "2027-01-15",
          "days_to_expiry": 342,
          "option_type": "CALL",
          "score": 30
        }
      ]
    },
    {
      "ticker": "CRSP",
      "current_price": 46.78,
      "signal": "SELL",
      "target_price": 53.29,
      "recommendation": "$50.0 CALL exp 2027-01-15 \u2192 Target $53.29",
      "options": [
        {
          "strike": 50.0,
          "bid": 9.9,
          "ask": 11.6,
          "mid_price": 10.75,
          "last_price": 9.4,
          "volume": 30,
          "open_interest": 938,
          "implied_volatility": 66.7,
          "delta": 0.45,
          "intrinsic": 0,
          "extrinsic": 10.75,
          "moneyness": -6.9,
          "moneyness_label": "OTM",
          "break_even": 60.75,
          "target_price": 53.29,
          "return_at_target": -69.4,
          "max_loss": -100,
          "leverage": 2.0,
          "daily_theta_pct": 0.292,
          "liquidity_score": 12.4,
          "risk_reward": 0,
          "expiry": "2027-01-15",
          "days_to_expiry": 342,
          "option_type": "CALL",
          "score": 32
        }
      ]
    },
    {
      "ticker": "DNA",
      "current_price": 9.04,
      "signal": "SELL",
      "target_price": 10.58,
      "recommendation": "$3.0 CALL exp 2027-01-15 \u2192 Target $10.58",
      "options": [
        {
          "strike": 3.0,
          "bid": 5.1,
          "ask": 6.8,
          "mid_price": 5.95,
          "last_price": 7.3,
          "volume": 1,
          "open_interest": 73,
          "implied_volatility": 143.0,
          "delta": 0.8,
          "intrinsic": 6.04,
          "extrinsic": -0.09,
          "moneyness": 66.8,
          "moneyness_label": "ITM",
          "break_even": 8.95,
          "target_price": 10.58,
          "return_at_target": 27.4,
          "max_loss": -100,
          "leverage": 1.2,
          "daily_theta_pct": -0.004,
          "liquidity_score": 0.8,
          "risk_reward": 0.27,
          "expiry": "2027-01-15",
          "days_to_expiry": 342,
          "option_type": "CALL",
          "score": 21.9
        }
      ]
    },
    {
      "ticker": "RXRX",
      "current_price": 3.77,
      "signal": "HOLD",
      "target_price": 4.34,
      "recommendation": "$4.0 CALL exp 2027-01-15 \u2192 Target $4.34",
      "options": [
        {
          "strike": 4.0,
          "bid": 1.02,
          "ask": 2.1,
          "mid_price": 1.56,
          "last_price": 1.33,
          "volume": 379,
          "open_interest": 3171,
          "implied_volatility": 117.5,
          "delta": 0.45,
          "intrinsic": 0,
          "extrinsic": 1.56,
          "moneyness": -6.1,
          "moneyness_label": "OTM",
          "break_even": 5.56,
          "target_price": 4.34,
          "return_at_target": -78.2,
          "max_loss": -100,
          "leverage": 1.1,
          "daily_theta_pct": 0.292,
          "liquidity_score": 69.6,
          "risk_reward": 0,
          "expiry": "2027-01-15",
          "days_to_expiry": 342,
          "option_type": "CALL",
          "score": 35
        }
      ]
    },
    {
      "ticker": "ASTS",
      "current_price": 98.07,
      "signal": "HOLD",
      "target_price": 123.22,
      "recommendation": "$100.0 CALL exp 2027-01-15 \u2192 Target $123.22",
      "options": [
        {
          "strike": 100.0,
          "bid": 32.95,
          "ask": 35.9,
          "mid_price": 34.42,
          "last_price": 34.0,
          "volume": 2,
          "open_interest": 3441,
          "implied_volatility": 95.4,
          "delta": 0.45,
          "intrinsic": 0,
          "extrinsic": 34.42,
          "moneyness": -2.0,
          "moneyness_label": "ATM",
          "break_even": 134.43,
          "target_price": 123.22,
          "return_at_target": -32.5,
          "max_loss": -100,
          "leverage": 1.3,
          "daily_theta_pct": 0.292,
          "liquidity_score": 34.6,
          "risk_reward": 0,
          "expiry": "2027-01-15",
          "days_to_expiry": 342,
          "option_type": "CALL",
          "score": 33
        }
      ]
    },
    {
      "ticker": "IRDM",
      "current_price": 19.32,
      "signal": "HOLD",
      "recommendation": "No LEAPS available (options may not be listed)",
      "options": []
    },
    {
      "ticker": "RKLB",
      "current_price": 68.53,
      "signal": "HOLD",
      "target_price": 84.17,
      "recommendation": "$1.0 CALL exp 2026-12-18 \u2192 Target $84.17",
      "options": [
        {
          "strike": 1.0,
          "bid": 42.0,
          "ask": 47.0,
          "mid_price": 44.5,
          "last_price": 52.5,
          "volume": 9,
          "open_interest": 15,
          "implied_volatility": 0.0,
          "delta": 0.8,
          "intrinsic": 67.53,
          "extrinsic": -23.03,
          "moneyness": 98.5,
          "moneyness_label": "ITM",
          "break_even": 45.5,
          "target_price": 84.17,
          "return_at_target": 86.9,
          "max_loss": -100,
          "leverage": 1.2,
          "daily_theta_pct": -0.165,
          "liquidity_score": 1.1,
          "risk_reward": 0.87,
          "expiry": "2026-12-18",
          "days_to_expiry": 314,
          "option_type": "CALL",
          "score": 41.7
        }
      ]
    },
    {
      "ticker": "ENPH",
      "current_price": 49.11,
      "signal": "BUY",
      "target_price": 56.53,
      "recommendation": "$15.0 CALL exp 2026-12-18 \u2192 Target $56.53",
      "options": [
        {
          "strike": 15.0,
          "bid": 22.05,
          "ask": 25.15,
          "mid_price": 23.6,
          "last_price": 19.75,
          "volume": 2,
          "open_interest": 74,
          "implied_volatility": 0.0,
          "delta": 0.8,
          "intrinsic": 34.11,
          "extrinsic": -10.51,
          "moneyness": 69.5,
          "moneyness_label": "ITM",
          "break_even": 38.6,
          "target_price": 56.53,
          "return_at_target": 76.0,
          "max_loss": -100,
          "leverage": 1.7,
          "daily_theta_pct": -0.142,
          "liquidity_score": 0.9,
          "risk_reward": 0.76,
          "expiry": "2026-12-18",
          "days_to_expiry": 314,
          "option_type": "CALL",
          "score": 39.0
        }
      ]
    },
    {
      "ticker": "FSLR",
      "current_price": 223.63,
      "signal": "HOLD",
      "target_price": 250.25,
      "recommendation": "$220.0 CALL exp 2027-01-15 \u2192 Target $250.25",
      "options": [
        {
          "strike": 220.0,
          "bid": 55.0,
          "ask": 59.5,
          "mid_price": 57.25,
          "last_price": 59.18,
          "volume": 4,
          "open_interest": 2218,
          "implied_volatility": 65.9,
          "delta": 0.55,
          "intrinsic": 3.63,
          "extrinsic": 53.62,
          "moneyness": 1.6,
          "moneyness_label": "ATM",
          "break_even": 277.25,
          "target_price": 250.25,
          "return_at_target": -47.2,
          "max_loss": -100,
          "leverage": 2.1,
          "daily_theta_pct": 0.274,
          "liquidity_score": 22.6,
          "risk_reward": 0,
          "expiry": "2027-01-15",
          "days_to_expiry": 342,
          "option_type": "CALL",
          "score": 34
        }
      ]
    },
    {
      "ticker": "QS",
      "current_price": 8.2,
      "signal": "HOLD",
      "target_price": 9.57,
      "recommendation": "$9.0 CALL exp 2026-08-21 \u2192 Target $9.57",
      "options": [
        {
          "strike": 9.0,
          "bid": 1.8,
          "ask": 1.97,
          "mid_price": 1.89,
          "last_price": 1.97,
          "volume": 20,
          "open_interest": 704,
          "implied_volatility": 91.3,
          "delta": 0.45,
          "intrinsic": 0,
          "extrinsic": 1.89,
          "moneyness": -9.8,
          "moneyness_label": "OTM",
          "break_even": 10.88,
          "target_price": 9.57,
          "return_at_target": -69.8,
          "max_loss": -100,
          "leverage": 2.0,
          "daily_theta_pct": 0.513,
          "liquidity_score": 9.0,
          "risk_reward": 0,
          "expiry": "2026-08-21",
          "days_to_expiry": 195,
          "option_type": "CALL",
          "score": 26
        }
      ]
    },
    {
      "ticker": "LEU",
      "current_price": 254.54,
      "signal": "HOLD",
      "target_price": 319.06,
      "recommendation": "$250.0 CALL exp 2026-12-18 \u2192 Target $319.06",
      "options": [
        {
          "strike": 250.0,
          "bid": 86.5,
          "ask": 90.5,
          "mid_price": 88.5,
          "last_price": 100.0,
          "volume": 1,
          "open_interest": 42,
          "implied_volatility": 94.3,
          "delta": 0.55,
          "intrinsic": 4.54,
          "extrinsic": 83.96,
          "moneyness": 1.8,
          "moneyness_label": "ATM",
          "break_even": 338.5,
          "target_price": 319.06,
          "return_at_target": -22.0,
          "max_loss": -100,
          "leverage": 1.6,
          "daily_theta_pct": 0.302,
          "liquidity_score": 0.5,
          "risk_reward": 0,
          "expiry": "2026-12-18",
          "days_to_expiry": 314,
          "option_type": "CALL",
          "score": 30
        }
      ]
    }
  ]
}